<input>
<table>
<tableRow text="WTARZLRNHB" font="Gotham" border="full" textIndent="right"></tableRow>
<tableRow text="DROKZQMALW" font="Gotham" border="full" textIndent="right"></tableRow>
<tableRow text="OSKWUSJIJE" font="Gotham" border="full" textIndent="right"></tableRow>
<tableRow text="TDSMSRPDNH" font="Gotham" border="full" textIndent="right"></tableRow>
<tableRow text="IODQFDOSLZ" font="Gotham" border="full" textIndent="right"></tableRow>
<tableRow text="GCDBFZOFLL" font="Gotham" border="full" textIndent="right"></tableRow>
<tableRow text="JEAOKQYSAV" font="Gotham" border="full" textIndent="right"></tableRow>
<tableRow text="GELJVTNIOC" font="Gotham" border="full" textIndent="right"></tableRow>
</table>
<table>
<tableRow text="EPIQMRULLG" font="Comic Sans MS" border="none" textIndent="center"></tableRow>
<tableRow text="CVNDJAHYBS" font="Comic Sans MS" border="none" textIndent="center"></tableRow>
<tableRow text="QNDCBUONPQ" font="Comic Sans MS" border="none" textIndent="center"></tableRow>
<tableRow text="VDKJDSVRHP" font="Comic Sans MS" border="none" textIndent="center"></tableRow>
<tableRow text="HIKIYRHOBS" font="Comic Sans MS" border="none" textIndent="center"></tableRow>
<tableRow text="VFWDUTPZEK" font="Comic Sans MS" border="none" textIndent="center"></tableRow>
<tableRow text="ZKWWKKYDWK" font="Comic Sans MS" border="none" textIndent="center"></tableRow>
</table>
<table>
<tableRow text="KSCILYGGSB" font="Arial" border="row" textIndent="left"></tableRow>
<tableRow text="UWYPXDNVAH" font="Arial" border="row" textIndent="left"></tableRow>
<tableRow text="LAQEASHWXL" font="Arial" border="row" textIndent="left"></tableRow>
<tableRow text="IOPCJFAAOA" font="Arial" border="row" textIndent="left"></tableRow>
<tableRow text="XBDAJIFPFI" font="Arial" border="row" textIndent="left"></tableRow>
<tableRow text="WQIBFRRXVP" font="Arial" border="row" textIndent="left"></tableRow>
<tableRow text="YSQMRPNQFY" font="Arial" border="row" textIndent="left"></tableRow>
<tableRow text="MTZIPTZLVH" font="Arial" border="row" textIndent="left"></tableRow>
<tableRow text="ZIHRBVYKYV" font="Arial" border="row" textIndent="left"></tableRow>
<tableRow text="NZGTEOIDOR" font="Arial" border="row" textIndent="left"></tableRow>
<tableRow text="KSWAVAALPL" font="Arial" border="row" textIndent="left"></tableRow>
<tableRow text="IELHCJJBWL" font="Arial" border="row" textIndent="left"></tableRow>
<tableRow text="DTNKNBEAYV" font="Arial" border="row" textIndent="left"></tableRow>
<tableRow text="ZGEIHFLNQH" font="Arial" border="row" textIndent="left"></tableRow>
</table>
<table>
<tableRow text="MNVOKVZRCZ" font="Comic Sans MS" border="none" textIndent="center"></tableRow>
<tableRow text="CEPJGOAIXB" font="Comic Sans MS" border="none" textIndent="center"></tableRow>
</table>
<table>
<tableRow text="UKCKSVSDMP" font="Arial" border="none" textIndent="right"></tableRow>
<tableRow text="UJIUIOBFRT" font="Arial" border="none" textIndent="right"></tableRow>
<tableRow text="GTIHMKLEDT" font="Arial" border="none" textIndent="right"></tableRow>
</table>
<table>
<tableRow text="GBXMBIMHQJ" font="Comic Sans MS" border="full" textIndent="right"></tableRow>
<tableRow text="QZNHWECHNH" font="Comic Sans MS" border="full" textIndent="right"></tableRow>
<tableRow text="XNQKRYYVLW" font="Comic Sans MS" border="full" textIndent="right"></tableRow>
<tableRow text="WYMUOFQLZB" font="Comic Sans MS" border="full" textIndent="right"></tableRow>
<tableRow text="OHISOLMDLN" font="Comic Sans MS" border="full" textIndent="right"></tableRow>
<tableRow text="NJUKCRMDDT" font="Comic Sans MS" border="full" textIndent="right"></tableRow>
<tableRow text="RTHFOXHMFF" font="Comic Sans MS" border="full" textIndent="right"></tableRow>
<tableRow text="YIROWMAUXL" font="Comic Sans MS" border="full" textIndent="right"></tableRow>
<tableRow text="XTXVYDZNNJ" font="Comic Sans MS" border="full" textIndent="right"></tableRow>
<tableRow text="DBPQULFSCW" font="Comic Sans MS" border="full" textIndent="right"></tableRow>
<tableRow text="ERHRPUPIIV" font="Comic Sans MS" border="full" textIndent="right"></tableRow>
<tableRow text="XJSMMKYBGU" font="Comic Sans MS" border="full" textIndent="right"></tableRow>
<tableRow text="KXJOWGUUSB" font="Comic Sans MS" border="full" textIndent="right"></tableRow>
<tableRow text="IGEEJALODU" font="Comic Sans MS" border="full" textIndent="right"></tableRow>
<tableRow text="ZWZGSEDQXV" font="Comic Sans MS" border="full" textIndent="right"></tableRow>
<tableRow text="PQESFIPUBC" font="Comic Sans MS" border="full" textIndent="right"></tableRow>
<tableRow text="FAJHPNUFWU" font="Comic Sans MS" border="full" textIndent="right"></tableRow>
</table>
<table>
<tableRow text="ETCUWMHRNP" font="Comic Sans MS" border="full" textIndent="left"></tableRow>
<tableRow text="THVTWIKTEZ" font="Comic Sans MS" border="full" textIndent="left"></tableRow>
<tableRow text="MBCXBKOLIQ" font="Comic Sans MS" border="full" textIndent="left"></tableRow>
<tableRow text="YCOVKDKIZV" font="Comic Sans MS" border="full" textIndent="left"></tableRow>
<tableRow text="LBFAJXAFLU" font="Comic Sans MS" border="full" textIndent="left"></tableRow>
<tableRow text="FJZJRUXJXG" font="Comic Sans MS" border="full" textIndent="left"></tableRow>
<tableRow text="SVXYUVSFBT" font="Comic Sans MS" border="full" textIndent="left"></tableRow>
<tableRow text="RHNCBQGMLZ" font="Comic Sans MS" border="full" textIndent="left"></tableRow>
<tableRow text="LIEFPPDFYD" font="Comic Sans MS" border="full" textIndent="left"></tableRow>
<tableRow text="VTJGQOHSHJ" font="Comic Sans MS" border="full" textIndent="left"></tableRow>
<tableRow text="ZRFEMLQITL" font="Comic Sans MS" border="full" textIndent="left"></tableRow>
<tableRow text="OUKWISDXIU" font="Comic Sans MS" border="full" textIndent="left"></tableRow>
<tableRow text="AJVVFNJXAP" font="Comic Sans MS" border="full" textIndent="left"></tableRow>
<tableRow text="DKZPACSINY" font="Comic Sans MS" border="full" textIndent="left"></tableRow>
<tableRow text="BJDUGJYZIQ" font="Comic Sans MS" border="full" textIndent="left"></tableRow>
<tableRow text="UOLYDWCCQV" font="Comic Sans MS" border="full" textIndent="left"></tableRow>
<tableRow text="WXNRRPVBRG" font="Comic Sans MS" border="full" textIndent="left"></tableRow>
<tableRow text="GQPREVAKFD" font="Comic Sans MS" border="full" textIndent="left"></tableRow>
</table>
<table>
<tableRow text="MFOZDIWCLJ" font="Arial" border="full" textIndent="right"></tableRow>
<tableRow text="GWBMNHAXQP" font="Arial" border="full" textIndent="right"></tableRow>
<tableRow text="ONLVGFGBUG" font="Arial" border="full" textIndent="right"></tableRow>
<tableRow text="WBKXGOZHQQ" font="Arial" border="full" textIndent="right"></tableRow>
<tableRow text="BUYFTGFUZX" font="Arial" border="full" textIndent="right"></tableRow>
<tableRow text="EDZVFLDMYK" font="Arial" border="full" textIndent="right"></tableRow>
<tableRow text="SCZXYBGQHS" font="Arial" border="full" textIndent="right"></tableRow>
<tableRow text="QHFMCHXDST" font="Arial" border="full" textIndent="right"></tableRow>
<tableRow text="NTMKMSUUZA" font="Arial" border="full" textIndent="right"></tableRow>
<tableRow text="GRTTXSHXWR" font="Arial" border="full" textIndent="right"></tableRow>
<tableRow text="BTANNJBMQM" font="Arial" border="full" textIndent="right"></tableRow>
<tableRow text="TAREUPTVBK" font="Arial" border="full" textIndent="right"></tableRow>
<tableRow text="TATAUAANVS" font="Arial" border="full" textIndent="right"></tableRow>
</table>
<table>
<tableRow text="YVMMTRBFDU" font="Comic Sans MS" border="none" textIndent="right"></tableRow>
<tableRow text="DRGGAQDGRE" font="Comic Sans MS" border="none" textIndent="right"></tableRow>
<tableRow text="JUQAUPORMJ" font="Comic Sans MS" border="none" textIndent="right"></tableRow>
<tableRow text="QUCISDCUMP" font="Comic Sans MS" border="none" textIndent="right"></tableRow>
<tableRow text="ZTEBLTVYWR" font="Comic Sans MS" border="none" textIndent="right"></tableRow>
<tableRow text="ISNITDJKZP" font="Comic Sans MS" border="none" textIndent="right"></tableRow>
<tableRow text="GJVMXSYTDN" font="Comic Sans MS" border="none" textIndent="right"></tableRow>
<tableRow text="MFKHNJBFUH" font="Comic Sans MS" border="none" textIndent="right"></tableRow>
<tableRow text="DFESMJFHCU" font="Comic Sans MS" border="none" textIndent="right"></tableRow>
<tableRow text="HCCERMMRON" font="Comic Sans MS" border="none" textIndent="right"></tableRow>
</table>
<table>
<tableRow text="TGTXWJQXPT" font="Comic Sans MS" border="none" textIndent="right"></tableRow>
<tableRow text="LIMPXNBKGB" font="Comic Sans MS" border="none" textIndent="right"></tableRow>
<tableRow text="DJMZPDWISQ" font="Comic Sans MS" border="none" textIndent="right"></tableRow>
<tableRow text="SAOSLSLXYU" font="Comic Sans MS" border="none" textIndent="right"></tableRow>
<tableRow text="VFRXRKXOLD" font="Comic Sans MS" border="none" textIndent="right"></tableRow>
<tableRow text="BEWINIPJUR" font="Comic Sans MS" border="none" textIndent="right"></tableRow>
<tableRow text="PPJZDLTWSZ" font="Comic Sans MS" border="none" textIndent="right"></tableRow>
<tableRow text="YAGGDCPQSI" font="Comic Sans MS" border="none" textIndent="right"></tableRow>
<tableRow text="PTNZIUVGWG" font="Comic Sans MS" border="none" textIndent="right"></tableRow>
<tableRow text="PTLIIAWXYD" font="Comic Sans MS" border="none" textIndent="right"></tableRow>
<tableRow text="QZHTDZTKCZ" font="Comic Sans MS" border="none" textIndent="right"></tableRow>
<tableRow text="KWCHKUUDNP" font="Comic Sans MS" border="none" textIndent="right"></tableRow>
<tableRow text="TEABWHJGSA" font="Comic Sans MS" border="none" textIndent="right"></tableRow>
<tableRow text="ABUEWHOXYT" font="Comic Sans MS" border="none" textIndent="right"></tableRow>
<tableRow text="MIKWKGTBAU" font="Comic Sans MS" border="none" textIndent="right"></tableRow>
<tableRow text="AMMHRTDLMY" font="Comic Sans MS" border="none" textIndent="right"></tableRow>
<tableRow text="SOMYNRSQWQ" font="Comic Sans MS" border="none" textIndent="right"></tableRow>
<tableRow text="UPIPRIRHAE" font="Comic Sans MS" border="none" textIndent="right"></tableRow>
<tableRow text="WFXNMMXZKQ" font="Comic Sans MS" border="none" textIndent="right"></tableRow>
</table>
<table>
<tableRow text="IEZJOGNVKB" font="Comic Sans MS" border="full" textIndent="center"></tableRow>
<tableRow text="WXZENRSAAV" font="Comic Sans MS" border="full" textIndent="center"></tableRow>
<tableRow text="LZYGPTXOSJ" font="Comic Sans MS" border="full" textIndent="center"></tableRow>
<tableRow text="RFBITUKNNE" font="Comic Sans MS" border="full" textIndent="center"></tableRow>
<tableRow text="LQSEIMGLIZ" font="Comic Sans MS" border="full" textIndent="center"></tableRow>
<tableRow text="ESENSLUZYY" font="Comic Sans MS" border="full" textIndent="center"></tableRow>
</table>
<table>
<tableRow text="TKVHTVUHDT" font="Gotham" border="full" textIndent="right"></tableRow>
<tableRow text="URGQPHFIPD" font="Gotham" border="full" textIndent="right"></tableRow>
<tableRow text="EAPVUDNHOK" font="Gotham" border="full" textIndent="right"></tableRow>
<tableRow text="AULTMVIFPW" font="Gotham" border="full" textIndent="right"></tableRow>
<tableRow text="ODXXHIPFHX" font="Gotham" border="full" textIndent="right"></tableRow>
<tableRow text="IXNYULRGND" font="Gotham" border="full" textIndent="right"></tableRow>
<tableRow text="MZKZHUQKUV" font="Gotham" border="full" textIndent="right"></tableRow>
<tableRow text="RQVGEUSZUW" font="Gotham" border="full" textIndent="right"></tableRow>
</table>
<table>
<tableRow text="TQHKDYPNZZ" font="Comic Sans MS" border="full" textIndent="center"></tableRow>
<tableRow text="RKRVRBARBX" font="Comic Sans MS" border="full" textIndent="center"></tableRow>
<tableRow text="RLSBWUATZS" font="Comic Sans MS" border="full" textIndent="center"></tableRow>
<tableRow text="ALPVVTADMT" font="Comic Sans MS" border="full" textIndent="center"></tableRow>
<tableRow text="ADFDHKLGYL" font="Comic Sans MS" border="full" textIndent="center"></tableRow>
<tableRow text="ZMRWRHXPIE" font="Comic Sans MS" border="full" textIndent="center"></tableRow>
<tableRow text="MKFMCXOCER" font="Comic Sans MS" border="full" textIndent="center"></tableRow>
<tableRow text="NDZUDTJCHV" font="Comic Sans MS" border="full" textIndent="center"></tableRow>
<tableRow text="EYFCOCXCBT" font="Comic Sans MS" border="full" textIndent="center"></tableRow>
<tableRow text="KPUSKIYWJI" font="Comic Sans MS" border="full" textIndent="center"></tableRow>
<tableRow text="YKDOFBTMBU" font="Comic Sans MS" border="full" textIndent="center"></tableRow>
<tableRow text="OTBWWRZKLO" font="Comic Sans MS" border="full" textIndent="center"></tableRow>
<tableRow text="AYJHIBZFRA" font="Comic Sans MS" border="full" textIndent="center"></tableRow>
<tableRow text="OBKOPCUFGC" font="Comic Sans MS" border="full" textIndent="center"></tableRow>
</table>
<table>
<tableRow text="CZUJAVQGAQ" font="Comic Sans MS" border="none" textIndent="left"></tableRow>
<tableRow text="KOKIJVCZGE" font="Comic Sans MS" border="none" textIndent="left"></tableRow>
<tableRow text="PMJVEIOVFZ" font="Comic Sans MS" border="none" textIndent="left"></tableRow>
<tableRow text="SERUQFIYQW" font="Comic Sans MS" border="none" textIndent="left"></tableRow>
<tableRow text="THQQCMOODX" font="Comic Sans MS" border="none" textIndent="left"></tableRow>
<tableRow text="MOBFTMBBBV" font="Comic Sans MS" border="none" textIndent="left"></tableRow>
<tableRow text="OVFNZTVWTV" font="Comic Sans MS" border="none" textIndent="left"></tableRow>
<tableRow text="RIXPKHXBLI" font="Comic Sans MS" border="none" textIndent="left"></tableRow>
<tableRow text="ZMHORNDWEP" font="Comic Sans MS" border="none" textIndent="left"></tableRow>
<tableRow text="QOTFVBGMFX" font="Comic Sans MS" border="none" textIndent="left"></tableRow>
</table>
<table>
<tableRow text="URJUKDIAKR" font="Comic Sans MS" border="full" textIndent="right"></tableRow>
<tableRow text="OTAVHXVZAP" font="Comic Sans MS" border="full" textIndent="right"></tableRow>
<tableRow text="FSEHUCHXBP" font="Comic Sans MS" border="full" textIndent="right"></tableRow>
<tableRow text="ICXVBHHRFC" font="Comic Sans MS" border="full" textIndent="right"></tableRow>
<tableRow text="LEQOCBEUVZ" font="Comic Sans MS" border="full" textIndent="right"></tableRow>
</table>
<table>
<tableRow text="NWRYCDWLYP" font="Arial" border="column" textIndent="center"></tableRow>
<tableRow text="SIKNEKTDJN" font="Arial" border="column" textIndent="center"></tableRow>
<tableRow text="TKZGUEUNGX" font="Arial" border="column" textIndent="center"></tableRow>
<tableRow text="AQIGTHQJRB" font="Arial" border="column" textIndent="center"></tableRow>
<tableRow text="RABEQKSISC" font="Arial" border="column" textIndent="center"></tableRow>
<tableRow text="XKXTIDCSHF" font="Arial" border="column" textIndent="center"></tableRow>
<tableRow text="ZHVMMZVXTG" font="Arial" border="column" textIndent="center"></tableRow>
<tableRow text="YMJCIGBBUN" font="Arial" border="column" textIndent="center"></tableRow>
<tableRow text="YBEAIURKLL" font="Arial" border="column" textIndent="center"></tableRow>
<tableRow text="LDRLBCOMNY" font="Arial" border="column" textIndent="center"></tableRow>
<tableRow text="LIGIGQLEES" font="Arial" border="column" textIndent="center"></tableRow>
<tableRow text="QQITZXTVAA" font="Arial" border="column" textIndent="center"></tableRow>
<tableRow text="TSYQSGOUPX" font="Arial" border="column" textIndent="center"></tableRow>
<tableRow text="CIVWZOPKXF" font="Arial" border="column" textIndent="center"></tableRow>
<tableRow text="PEUQCTBDKQ" font="Arial" border="column" textIndent="center"></tableRow>
<tableRow text="LBOLBQQDAG" font="Arial" border="column" textIndent="center"></tableRow>
<tableRow text="RRJPNCGJML" font="Arial" border="column" textIndent="center"></tableRow>
<tableRow text="BTQXMAMYON" font="Arial" border="column" textIndent="center"></tableRow>
<tableRow text="VFODYHXSRU" font="Arial" border="column" textIndent="center"></tableRow>
</table>
<table>
<tableRow text="NEKWTBLUBF" font="Comic Sans MS" border="full" textIndent="left"></tableRow>
<tableRow text="SHYODPVZTV" font="Comic Sans MS" border="full" textIndent="left"></tableRow>
<tableRow text="XLNUOITRMY" font="Comic Sans MS" border="full" textIndent="left"></tableRow>
<tableRow text="TVEITZAJCK" font="Comic Sans MS" border="full" textIndent="left"></tableRow>
<tableRow text="HLBBRDVKGI" font="Comic Sans MS" border="full" textIndent="left"></tableRow>
<tableRow text="LWBBJTGWFB" font="Comic Sans MS" border="full" textIndent="left"></tableRow>
<tableRow text="JAHENJIVVH" font="Comic Sans MS" border="full" textIndent="left"></tableRow>
<tableRow text="XDLHEPNEYX" font="Comic Sans MS" border="full" textIndent="left"></tableRow>
<tableRow text="BHBOYOUSKZ" font="Comic Sans MS" border="full" textIndent="left"></tableRow>
<tableRow text="HDYHMFHWBM" font="Comic Sans MS" border="full" textIndent="left"></tableRow>
<tableRow text="LGODERQCRX" font="Comic Sans MS" border="full" textIndent="left"></tableRow>
<tableRow text="OCNVUMRQVJ" font="Comic Sans MS" border="full" textIndent="left"></tableRow>
<tableRow text="XPPBJBCPSH" font="Comic Sans MS" border="full" textIndent="left"></tableRow>
<tableRow text="TDYNYJMRWG" font="Comic Sans MS" border="full" textIndent="left"></tableRow>
</table>
<table>
<tableRow text="AAKEAQOPJW" font="Comic Sans MS" border="full" textIndent="left"></tableRow>
<tableRow text="JEQWBMPVAI" font="Comic Sans MS" border="full" textIndent="left"></tableRow>
<tableRow text="UAWIESOULJ" font="Comic Sans MS" border="full" textIndent="left"></tableRow>
<tableRow text="SNMKVTFPWK" font="Comic Sans MS" border="full" textIndent="left"></tableRow>
<tableRow text="LZPHGYIHTI" font="Comic Sans MS" border="full" textIndent="left"></tableRow>
<tableRow text="BVKDKLNWQO" font="Comic Sans MS" border="full" textIndent="left"></tableRow>
<tableRow text="CCRSSNNSRE" font="Comic Sans MS" border="full" textIndent="left"></tableRow>
<tableRow text="BQLYBCKXWT" font="Comic Sans MS" border="full" textIndent="left"></tableRow>
<tableRow text="XJRJUGWDLF" font="Comic Sans MS" border="full" textIndent="left"></tableRow>
<tableRow text="HPFMHICVNO" font="Comic Sans MS" border="full" textIndent="left"></tableRow>
<tableRow text="LZJQOCIBAE" font="Comic Sans MS" border="full" textIndent="left"></tableRow>
<tableRow text="ZDEHKTTBDV" font="Comic Sans MS" border="full" textIndent="left"></tableRow>
<tableRow text="RYWTFHYIKI" font="Comic Sans MS" border="full" textIndent="left"></tableRow>
<tableRow text="JGZKVSCGNB" font="Comic Sans MS" border="full" textIndent="left"></tableRow>
<tableRow text="LOIZMPOFND" font="Comic Sans MS" border="full" textIndent="left"></tableRow>
</table>
<table>
<tableRow text="HEMLMSZGPG" font="Arial" border="row" textIndent="right"></tableRow>
<tableRow text="NPHNLAPNIK" font="Arial" border="row" textIndent="right"></tableRow>
<tableRow text="QNDGBSZAAG" font="Arial" border="row" textIndent="right"></tableRow>
<tableRow text="URGTSOKUGF" font="Arial" border="row" textIndent="right"></tableRow>
<tableRow text="BHMXVWNGOE" font="Arial" border="row" textIndent="right"></tableRow>
<tableRow text="VGWIDEIQKJ" font="Arial" border="row" textIndent="right"></tableRow>
<tableRow text="SBNTOQCOCR" font="Arial" border="row" textIndent="right"></tableRow>
<tableRow text="NXYBAEWOUI" font="Arial" border="row" textIndent="right"></tableRow>
<tableRow text="FCMZHECBDY" font="Arial" border="row" textIndent="right"></tableRow>
<tableRow text="XGPKBWYBFA" font="Arial" border="row" textIndent="right"></tableRow>
<tableRow text="NRHAOVRCNO" font="Arial" border="row" textIndent="right"></tableRow>
<tableRow text="HTTMQBPZOB" font="Arial" border="row" textIndent="right"></tableRow>
<tableRow text="QNROGQUPEH" font="Arial" border="row" textIndent="right"></tableRow>
</table>
<table>
<tableRow text="GCLWNNHEFZ" font="Gotham" border="full" textIndent="center"></tableRow>
<tableRow text="MIXYRFDGEU" font="Gotham" border="full" textIndent="center"></tableRow>
<tableRow text="MUQOHMRCFZ" font="Gotham" border="full" textIndent="center"></tableRow>
<tableRow text="GEEONLGTLU" font="Gotham" border="full" textIndent="center"></tableRow>
<tableRow text="EUAMIJKZWH" font="Gotham" border="full" textIndent="center"></tableRow>
<tableRow text="AEEOJLJIKN" font="Gotham" border="full" textIndent="center"></tableRow>
</table>
<table>
<tableRow text="PYLPJFHYCB" font="Comic Sans MS" border="full" textIndent="right"></tableRow>
<tableRow text="MEZUWKCUBL" font="Comic Sans MS" border="full" textIndent="right"></tableRow>
</table>
<table>
<tableRow text="DNJCNRIBGY" font="Comic Sans MS" border="full" textIndent="left"></tableRow>
<tableRow text="TODJJHGJZY" font="Comic Sans MS" border="full" textIndent="left"></tableRow>
<tableRow text="GRCSQEGJUX" font="Comic Sans MS" border="full" textIndent="left"></tableRow>
</table>
<table>
<tableRow text="PIPCRSXLEY" font="Arial" border="full" textIndent="left"></tableRow>
<tableRow text="RBCEGQDFMZ" font="Arial" border="full" textIndent="left"></tableRow>
<tableRow text="XPMEGOSPQH" font="Arial" border="full" textIndent="left"></tableRow>
<tableRow text="AVLRNMNADJ" font="Arial" border="full" textIndent="left"></tableRow>
<tableRow text="OFDPHNXBRO" font="Arial" border="full" textIndent="left"></tableRow>
<tableRow text="IXBQMAIHEI" font="Arial" border="full" textIndent="left"></tableRow>
<tableRow text="XZOMJBWHHJ" font="Arial" border="full" textIndent="left"></tableRow>
<tableRow text="SNDJCCOQST" font="Arial" border="full" textIndent="left"></tableRow>
<tableRow text="NVCFPCEGQP" font="Arial" border="full" textIndent="left"></tableRow>
<tableRow text="LACBXJIMFB" font="Arial" border="full" textIndent="left"></tableRow>
<tableRow text="FBEVDFNIPY" font="Arial" border="full" textIndent="left"></tableRow>
<tableRow text="RRESVVFHUS" font="Arial" border="full" textIndent="left"></tableRow>
<tableRow text="ORQVIOAJGS" font="Arial" border="full" textIndent="left"></tableRow>
<tableRow text="MMQKYIYQBE" font="Arial" border="full" textIndent="left"></tableRow>
<tableRow text="OVNGKDRLZS" font="Arial" border="full" textIndent="left"></tableRow>
<tableRow text="THHILKAMHY" font="Arial" border="full" textIndent="left"></tableRow>
<tableRow text="IKUNUQXPTD" font="Arial" border="full" textIndent="left"></tableRow>
<tableRow text="LYESYVFGXU" font="Arial" border="full" textIndent="left"></tableRow>
<tableRow text="MKDSUGKFEA" font="Arial" border="full" textIndent="left"></tableRow>
</table>
<table>
<tableRow text="QYPUCOBVBM" font="Arial" border="row" textIndent="left"></tableRow>
<tableRow text="AMKVHLCJEM" font="Arial" border="row" textIndent="left"></tableRow>
<tableRow text="IJXPKMDRMZ" font="Arial" border="row" textIndent="left"></tableRow>
<tableRow text="FDJXIHAGOD" font="Arial" border="row" textIndent="left"></tableRow>
<tableRow text="UZAERQWQUL" font="Arial" border="row" textIndent="left"></tableRow>
</table>
<table>
<tableRow text="ZFSGPHMEHP" font="Gotham" border="full" textIndent="left"></tableRow>
<tableRow text="WVNCULJORB" font="Gotham" border="full" textIndent="left"></tableRow>
<tableRow text="MHNWABWHVN" font="Gotham" border="full" textIndent="left"></tableRow>
<tableRow text="NCVETPNZCE" font="Gotham" border="full" textIndent="left"></tableRow>
<tableRow text="WFCEKMQAQP" font="Gotham" border="full" textIndent="left"></tableRow>
<tableRow text="IFTEFFOWZR" font="Gotham" border="full" textIndent="left"></tableRow>
<tableRow text="LKYWXMHFRF" font="Gotham" border="full" textIndent="left"></tableRow>
<tableRow text="DKLXFZDSME" font="Gotham" border="full" textIndent="left"></tableRow>
<tableRow text="VXBFATVCUC" font="Gotham" border="full" textIndent="left"></tableRow>
<tableRow text="THYAORZTLZ" font="Gotham" border="full" textIndent="left"></tableRow>
<tableRow text="ADKCQNOADW" font="Gotham" border="full" textIndent="left"></tableRow>
</table>
<table>
<tableRow text="HRZCOHRVGT" font="Gotham" border="full" textIndent="center"></tableRow>
<tableRow text="ZXLFWVPDLY" font="Gotham" border="full" textIndent="center"></tableRow>
<tableRow text="JTZRPICWHG" font="Gotham" border="full" textIndent="center"></tableRow>
<tableRow text="HVYELSVFRA" font="Gotham" border="full" textIndent="center"></tableRow>
<tableRow text="UIOIAHLNEU" font="Gotham" border="full" textIndent="center"></tableRow>
<tableRow text="YMBMVSMHWZ" font="Gotham" border="full" textIndent="center"></tableRow>
<tableRow text="XAYXONEAKN" font="Gotham" border="full" textIndent="center"></tableRow>
<tableRow text="DMLJAWUXVD" font="Gotham" border="full" textIndent="center"></tableRow>
<tableRow text="DBFUZGJRZC" font="Gotham" border="full" textIndent="center"></tableRow>
<tableRow text="WYVILWUCLN" font="Gotham" border="full" textIndent="center"></tableRow>
</table>
<table>
<tableRow text="IVVHVUKRVQ" font="Comic Sans MS" border="none" textIndent="left"></tableRow>
<tableRow text="TJLPRXSRWX" font="Comic Sans MS" border="none" textIndent="left"></tableRow>
<tableRow text="YRWTBIOIPY" font="Comic Sans MS" border="none" textIndent="left"></tableRow>
<tableRow text="MXRPMLCVKZ" font="Comic Sans MS" border="none" textIndent="left"></tableRow>
<tableRow text="REYNCMFMQX" font="Comic Sans MS" border="none" textIndent="left"></tableRow>
<tableRow text="PQMQCGICPB" font="Comic Sans MS" border="none" textIndent="left"></tableRow>
<tableRow text="NYXFHIZPWZ" font="Comic Sans MS" border="none" textIndent="left"></tableRow>
<tableRow text="FNGTQZYLWQ" font="Comic Sans MS" border="none" textIndent="left"></tableRow>
<tableRow text="ENYXYULVFX" font="Comic Sans MS" border="none" textIndent="left"></tableRow>
<tableRow text="ZYSKIJTFBG" font="Comic Sans MS" border="none" textIndent="left"></tableRow>
<tableRow text="KJIYGCAXAF" font="Comic Sans MS" border="none" textIndent="left"></tableRow>
<tableRow text="BFBIBRGOGG" font="Comic Sans MS" border="none" textIndent="left"></tableRow>
<tableRow text="ULCULIWIUN" font="Comic Sans MS" border="none" textIndent="left"></tableRow>
<tableRow text="QRRXGXTXAW" font="Comic Sans MS" border="none" textIndent="left"></tableRow>
</table>
<table>
<tableRow text="HYZNNEWVZT" font="Arial" border="row" textIndent="center"></tableRow>
<tableRow text="VXCFMVKUNJ" font="Arial" border="row" textIndent="center"></tableRow>
<tableRow text="MMJQXYVTMJ" font="Arial" border="row" textIndent="center"></tableRow>
<tableRow text="XRYAPEEBRD" font="Arial" border="row" textIndent="center"></tableRow>
<tableRow text="DLQNARLMQO" font="Arial" border="row" textIndent="center"></tableRow>
<tableRow text="LFYACRLSQY" font="Arial" border="row" textIndent="center"></tableRow>
<tableRow text="YBGNCZUKIX" font="Arial" border="row" textIndent="center"></tableRow>
<tableRow text="WAFMWKNZZK" font="Arial" border="row" textIndent="center"></tableRow>
<tableRow text="VRIOJDULYT" font="Arial" border="row" textIndent="center"></tableRow>
<tableRow text="MWFUBJKCVS" font="Arial" border="row" textIndent="center"></tableRow>
<tableRow text="BJTCYAWIFB" font="Arial" border="row" textIndent="center"></tableRow>
<tableRow text="NSNKYADARN" font="Arial" border="row" textIndent="center"></tableRow>
<tableRow text="KWVMIBAKCP" font="Arial" border="row" textIndent="center"></tableRow>
<tableRow text="TYSESZSMDF" font="Arial" border="row" textIndent="center"></tableRow>
<tableRow text="OBACXBZLTB" font="Arial" border="row" textIndent="center"></tableRow>
<tableRow text="QENQNZELVV" font="Arial" border="row" textIndent="center"></tableRow>
<tableRow text="TUASIDBKUR" font="Arial" border="row" textIndent="center"></tableRow>
</table>
<table>
<tableRow text="YHCIWAUQEK" font="Arial" border="full" textIndent="center"></tableRow>
<tableRow text="GSYBATXNTA" font="Arial" border="full" textIndent="center"></tableRow>
<tableRow text="SIEOVIVPJD" font="Arial" border="full" textIndent="center"></tableRow>
</table>
<table>
<tableRow text="VNEHJIFOVZ" font="Comic Sans MS" border="none" textIndent="center"></tableRow>
<tableRow text="OYVRDQORKD" font="Comic Sans MS" border="none" textIndent="center"></tableRow>
<tableRow text="MOVILEZXCE" font="Comic Sans MS" border="none" textIndent="center"></tableRow>
<tableRow text="TPWHZSAGAA" font="Comic Sans MS" border="none" textIndent="center"></tableRow>
<tableRow text="DNXPCKPRIZ" font="Comic Sans MS" border="none" textIndent="center"></tableRow>
</table>
<table>
<tableRow text="AEFQTJRTRE" font="Arial" border="none" textIndent="center"></tableRow>
</table>
<table>
<tableRow text="APCZUYSHZZ" font="Times New Roman" border="full" textIndent="left"></tableRow>
</table>
<table>
<tableRow text="ZLMPRDSECI" font="Arial" border="row" textIndent="center"></tableRow>
<tableRow text="QWGOUFNJCH" font="Arial" border="row" textIndent="center"></tableRow>
<tableRow text="QWRUUUJDZP" font="Arial" border="row" textIndent="center"></tableRow>
<tableRow text="UMRYTUEXMJ" font="Arial" border="row" textIndent="center"></tableRow>
<tableRow text="HWXWTORCIX" font="Arial" border="row" textIndent="center"></tableRow>
<tableRow text="JYBPWQAADG" font="Arial" border="row" textIndent="center"></tableRow>
<tableRow text="QWOVXADEOA" font="Arial" border="row" textIndent="center"></tableRow>
<tableRow text="SBMMVRIRAD" font="Arial" border="row" textIndent="center"></tableRow>
<tableRow text="EFHVSJOHKT" font="Arial" border="row" textIndent="center"></tableRow>
<tableRow text="ASJNYYJUBA" font="Arial" border="row" textIndent="center"></tableRow>
<tableRow text="XZZUWQFQSA" font="Arial" border="row" textIndent="center"></tableRow>
<tableRow text="SMEPKSFVEY" font="Arial" border="row" textIndent="center"></tableRow>
</table>
<table>
<tableRow text="TGSEUQDRID" font="Comic Sans MS" border="none" textIndent="left"></tableRow>
<tableRow text="MYBMEBRRDV" font="Comic Sans MS" border="none" textIndent="left"></tableRow>
<tableRow text="KHXTWAUCYN" font="Comic Sans MS" border="none" textIndent="left"></tableRow>
<tableRow text="WXSXPQXJYN" font="Comic Sans MS" border="none" textIndent="left"></tableRow>
<tableRow text="TISONOGYTL" font="Comic Sans MS" border="none" textIndent="left"></tableRow>
<tableRow text="PFGYXZCVXU" font="Comic Sans MS" border="none" textIndent="left"></tableRow>
<tableRow text="VVYHKVXKXI" font="Comic Sans MS" border="none" textIndent="left"></tableRow>
<tableRow text="EEXKGAAEMA" font="Comic Sans MS" border="none" textIndent="left"></tableRow>
<tableRow text="IIJRNCMRDF" font="Comic Sans MS" border="none" textIndent="left"></tableRow>
<tableRow text="APARDPYPVL" font="Comic Sans MS" border="none" textIndent="left"></tableRow>
<tableRow text="RBEROXTBEX" font="Comic Sans MS" border="none" textIndent="left"></tableRow>
<tableRow text="MGKDINWAVL" font="Comic Sans MS" border="none" textIndent="left"></tableRow>
<tableRow text="EWXIHDICXQ" font="Comic Sans MS" border="none" textIndent="left"></tableRow>
</table>
<table>
<tableRow text="LATADXWCNE" font="Comic Sans MS" border="none" textIndent="center"></tableRow>
<tableRow text="LTKVYDICXA" font="Comic Sans MS" border="none" textIndent="center"></tableRow>
<tableRow text="YGOQEPNYPM" font="Comic Sans MS" border="none" textIndent="center"></tableRow>
<tableRow text="RFSDMNMHMF" font="Comic Sans MS" border="none" textIndent="center"></tableRow>
<tableRow text="OPZXZEZWDT" font="Comic Sans MS" border="none" textIndent="center"></tableRow>
<tableRow text="YGTEAZFRIP" font="Comic Sans MS" border="none" textIndent="center"></tableRow>
<tableRow text="HSBWQPISUN" font="Comic Sans MS" border="none" textIndent="center"></tableRow>
<tableRow text="EMDHMDXHHG" font="Comic Sans MS" border="none" textIndent="center"></tableRow>
<tableRow text="CIVJQRPOPU" font="Comic Sans MS" border="none" textIndent="center"></tableRow>
<tableRow text="RYHWFNESFL" font="Comic Sans MS" border="none" textIndent="center"></tableRow>
<tableRow text="CMVUGAEOCD" font="Comic Sans MS" border="none" textIndent="center"></tableRow>
<tableRow text="WXLYJCUXZZ" font="Comic Sans MS" border="none" textIndent="center"></tableRow>
<tableRow text="IAHFJADDFX" font="Comic Sans MS" border="none" textIndent="center"></tableRow>
<tableRow text="SAUNMHRCXD" font="Comic Sans MS" border="none" textIndent="center"></tableRow>
<tableRow text="HGAVRHBNLJ" font="Comic Sans MS" border="none" textIndent="center"></tableRow>
<tableRow text="LHKFFOLFXE" font="Comic Sans MS" border="none" textIndent="center"></tableRow>
<tableRow text="ALTNRZPJNX" font="Comic Sans MS" border="none" textIndent="center"></tableRow>
</table>
<table>
<tableRow text="FMWJYTOZBO" font="Comic Sans MS" border="full" textIndent="center"></tableRow>
<tableRow text="UFQNFQOROP" font="Comic Sans MS" border="full" textIndent="center"></tableRow>
<tableRow text="TVFYPQKCFH" font="Comic Sans MS" border="full" textIndent="center"></tableRow>
<tableRow text="HUVRKTKRWM" font="Comic Sans MS" border="full" textIndent="center"></tableRow>
<tableRow text="YYSPULKSRV" font="Comic Sans MS" border="full" textIndent="center"></tableRow>
<tableRow text="TLLUBSXYZK" font="Comic Sans MS" border="full" textIndent="center"></tableRow>
<tableRow text="AMQKLHMFAK" font="Comic Sans MS" border="full" textIndent="center"></tableRow>
<tableRow text="YGPZIKRKNC" font="Comic Sans MS" border="full" textIndent="center"></tableRow>
<tableRow text="QQXKNPZNLM" font="Comic Sans MS" border="full" textIndent="center"></tableRow>
<tableRow text="WJLAHCCBGG" font="Comic Sans MS" border="full" textIndent="center"></tableRow>
<tableRow text="IMQMCRAZFB" font="Comic Sans MS" border="full" textIndent="center"></tableRow>
<tableRow text="XMCZATTQMG" font="Comic Sans MS" border="full" textIndent="center"></tableRow>
<tableRow text="TVWCAXCKRS" font="Comic Sans MS" border="full" textIndent="center"></tableRow>
<tableRow text="AMHIEZPEYL" font="Comic Sans MS" border="full" textIndent="center"></tableRow>
<tableRow text="NDWJYJBBGG" font="Comic Sans MS" border="full" textIndent="center"></tableRow>
<tableRow text="FOKDBRLOWW" font="Comic Sans MS" border="full" textIndent="center"></tableRow>
<tableRow text="BJCOODYUDW" font="Comic Sans MS" border="full" textIndent="center"></tableRow>
<tableRow text="UXPTHKMKBJ" font="Comic Sans MS" border="full" textIndent="center"></tableRow>
<tableRow text="QBHUYHIHCL" font="Comic Sans MS" border="full" textIndent="center"></tableRow>
</table>
<table>
<tableRow text="VIEAHEMGYO" font="Gotham" border="full" textIndent="right"></tableRow>
</table>
<table>
<tableRow text="QBTZGDDFUX" font="Comic Sans MS" border="none" textIndent="left"></tableRow>
<tableRow text="ZFTQTYQSFM" font="Comic Sans MS" border="none" textIndent="left"></tableRow>
<tableRow text="WQCTQWPTKD" font="Comic Sans MS" border="none" textIndent="left"></tableRow>
<tableRow text="PKVJLUKHOP" font="Comic Sans MS" border="none" textIndent="left"></tableRow>
<tableRow text="AWDRFMELAD" font="Comic Sans MS" border="none" textIndent="left"></tableRow>
<tableRow text="NMUKJZMRWP" font="Comic Sans MS" border="none" textIndent="left"></tableRow>
<tableRow text="TAQFWSCOWO" font="Comic Sans MS" border="none" textIndent="left"></tableRow>
<tableRow text="PJLAKVVXLA" font="Comic Sans MS" border="none" textIndent="left"></tableRow>
<tableRow text="CJQQREWGQQ" font="Comic Sans MS" border="none" textIndent="left"></tableRow>
<tableRow text="DHZGOOPHYZ" font="Comic Sans MS" border="none" textIndent="left"></tableRow>
<tableRow text="BLZESJLIDL" font="Comic Sans MS" border="none" textIndent="left"></tableRow>
<tableRow text="ISIVGQOJIJ" font="Comic Sans MS" border="none" textIndent="left"></tableRow>
<tableRow text="MRZLSGDXLM" font="Comic Sans MS" border="none" textIndent="left"></tableRow>
<tableRow text="OJIYVFSZBL" font="Comic Sans MS" border="none" textIndent="left"></tableRow>
<tableRow text="GVIOCORWFJ" font="Comic Sans MS" border="none" textIndent="left"></tableRow>
<tableRow text="UJEBRJNPGM" font="Comic Sans MS" border="none" textIndent="left"></tableRow>
</table>
<table>
<tableRow text="GMCIPTXPIR" font="Arial" border="column" textIndent="right"></tableRow>
<tableRow text="ZCFXFMYULD" font="Arial" border="column" textIndent="right"></tableRow>
<tableRow text="ZRYWAPHRTN" font="Arial" border="column" textIndent="right"></tableRow>
</table>
<table>
<tableRow text="YEWQQMAZBD" font="Arial" border="row" textIndent="center"></tableRow>
<tableRow text="YSSYAFSHHA" font="Arial" border="row" textIndent="center"></tableRow>
<tableRow text="CPOAZKOIVQ" font="Arial" border="row" textIndent="center"></tableRow>
<tableRow text="UTOEVGGMZX" font="Arial" border="row" textIndent="center"></tableRow>
<tableRow text="YFKDPGJVRT" font="Arial" border="row" textIndent="center"></tableRow>
</table>
<table>
<tableRow text="DAWKTPMREY" font="Arial" border="full" textIndent="right"></tableRow>
<tableRow text="NOPYMLARED" font="Arial" border="full" textIndent="right"></tableRow>
<tableRow text="PLXUDADFPG" font="Arial" border="full" textIndent="right"></tableRow>
<tableRow text="XTGYEQYWSL" font="Arial" border="full" textIndent="right"></tableRow>
<tableRow text="ZTZBNCINGO" font="Arial" border="full" textIndent="right"></tableRow>
<tableRow text="ZKHETLWKYG" font="Arial" border="full" textIndent="right"></tableRow>
<tableRow text="NQSEJDNAOL" font="Arial" border="full" textIndent="right"></tableRow>
<tableRow text="FUOKMVPGXG" font="Arial" border="full" textIndent="right"></tableRow>
<tableRow text="XCYLCUGEMR" font="Arial" border="full" textIndent="right"></tableRow>
<tableRow text="FYDHWXHTJU" font="Arial" border="full" textIndent="right"></tableRow>
<tableRow text="REUWZJCPNV" font="Arial" border="full" textIndent="right"></tableRow>
</table>
<table>
<tableRow text="QDFHURINLY" font="Arial" border="none" textIndent="center"></tableRow>
<tableRow text="YWZLPTLIKY" font="Arial" border="none" textIndent="center"></tableRow>
<tableRow text="EAMSNAZTDY" font="Arial" border="none" textIndent="center"></tableRow>
</table>
<table>
<tableRow text="QSNSSPANGI" font="Comic Sans MS" border="none" textIndent="center"></tableRow>
<tableRow text="JUWJEEVSIA" font="Comic Sans MS" border="none" textIndent="center"></tableRow>
<tableRow text="XLOAVVUDWB" font="Comic Sans MS" border="none" textIndent="center"></tableRow>
<tableRow text="FQRLUTOQQG" font="Comic Sans MS" border="none" textIndent="center"></tableRow>
<tableRow text="KLXQIUAANX" font="Comic Sans MS" border="none" textIndent="center"></tableRow>
<tableRow text="PYSKBLYLHG" font="Comic Sans MS" border="none" textIndent="center"></tableRow>
<tableRow text="WQMYGFXZZH" font="Comic Sans MS" border="none" textIndent="center"></tableRow>
<tableRow text="BEFYNKDBKQ" font="Comic Sans MS" border="none" textIndent="center"></tableRow>
<tableRow text="JQTIZUBHXU" font="Comic Sans MS" border="none" textIndent="center"></tableRow>
</table>
<table>
<tableRow text="MXTAMSOAHE" font="Comic Sans MS" border="full" textIndent="center"></tableRow>
</table>
<table>
<tableRow text="VKRXDTZABY" font="Comic Sans MS" border="none" textIndent="center"></tableRow>
<tableRow text="MAQAATVFWV" font="Comic Sans MS" border="none" textIndent="center"></tableRow>
<tableRow text="DXNRJZHLYF" font="Comic Sans MS" border="none" textIndent="center"></tableRow>
<tableRow text="FLZAXCFAWH" font="Comic Sans MS" border="none" textIndent="center"></tableRow>
<tableRow text="XVHJGRJNWJ" font="Comic Sans MS" border="none" textIndent="center"></tableRow>
<tableRow text="UIXGECZERI" font="Comic Sans MS" border="none" textIndent="center"></tableRow>
<tableRow text="PAHLZBAEZD" font="Comic Sans MS" border="none" textIndent="center"></tableRow>
<tableRow text="PUPNDIJKZV" font="Comic Sans MS" border="none" textIndent="center"></tableRow>
<tableRow text="VSUGEBYVUF" font="Comic Sans MS" border="none" textIndent="center"></tableRow>
<tableRow text="NUDJYRGMJU" font="Comic Sans MS" border="none" textIndent="center"></tableRow>
<tableRow text="PYUUBKIOBQ" font="Comic Sans MS" border="none" textIndent="center"></tableRow>
<tableRow text="HMXDGHBPIV" font="Comic Sans MS" border="none" textIndent="center"></tableRow>
<tableRow text="VECZEPNUTD" font="Comic Sans MS" border="none" textIndent="center"></tableRow>
<tableRow text="WSYVDSNDYT" font="Comic Sans MS" border="none" textIndent="center"></tableRow>
<tableRow text="DIDXVPVNAA" font="Comic Sans MS" border="none" textIndent="center"></tableRow>
<tableRow text="EEHSBGQLOD" font="Comic Sans MS" border="none" textIndent="center"></tableRow>
<tableRow text="LABCJZRYCR" font="Comic Sans MS" border="none" textIndent="center"></tableRow>
</table>
<table>
<tableRow text="STNJVTOMJS" font="Arial" border="row" textIndent="center"></tableRow>
<tableRow text="DIDDNMEYWW" font="Arial" border="row" textIndent="center"></tableRow>
<tableRow text="GPULDFJNIM" font="Arial" border="row" textIndent="center"></tableRow>
<tableRow text="TAOIMBSXSI" font="Arial" border="row" textIndent="center"></tableRow>
<tableRow text="JEEYGAMRRS" font="Arial" border="row" textIndent="center"></tableRow>
<tableRow text="OLCHZWVJBS" font="Arial" border="row" textIndent="center"></tableRow>
<tableRow text="AVWWPNHBLO" font="Arial" border="row" textIndent="center"></tableRow>
</table>
<table>
<tableRow text="FWHGENVEGO" font="Times New Roman" border="full" textIndent="center"></tableRow>
<tableRow text="OXMPGEHMNC" font="Times New Roman" border="full" textIndent="center"></tableRow>
<tableRow text="RGKZPKVWQP" font="Times New Roman" border="full" textIndent="center"></tableRow>
<tableRow text="ORRAJOZQIN" font="Times New Roman" border="full" textIndent="center"></tableRow>
<tableRow text="HSECVEYVYY" font="Times New Roman" border="full" textIndent="center"></tableRow>
</table>
<table>
<tableRow text="MFAMAEFMVP" font="Comic Sans MS" border="full" textIndent="left"></tableRow>
<tableRow text="JUCSYEMMJG" font="Comic Sans MS" border="full" textIndent="left"></tableRow>
<tableRow text="LWONJHBTYZ" font="Comic Sans MS" border="full" textIndent="left"></tableRow>
<tableRow text="MNTITURYMH" font="Comic Sans MS" border="full" textIndent="left"></tableRow>
<tableRow text="BTSQWQXQLD" font="Comic Sans MS" border="full" textIndent="left"></tableRow>
<tableRow text="DSDINGWDVV" font="Comic Sans MS" border="full" textIndent="left"></tableRow>
<tableRow text="GBWOUNMXUV" font="Comic Sans MS" border="full" textIndent="left"></tableRow>
<tableRow text="SOGZJYLWGS" font="Comic Sans MS" border="full" textIndent="left"></tableRow>
<tableRow text="PLWABJXPAD" font="Comic Sans MS" border="full" textIndent="left"></tableRow>
<tableRow text="IYGABUUPEA" font="Comic Sans MS" border="full" textIndent="left"></tableRow>
<tableRow text="YZJSUZPRGG" font="Comic Sans MS" border="full" textIndent="left"></tableRow>
<tableRow text="XBSUBUZEFX" font="Comic Sans MS" border="full" textIndent="left"></tableRow>
<tableRow text="BCGLGLMNNY" font="Comic Sans MS" border="full" textIndent="left"></tableRow>
<tableRow text="XUQPEVHKSE" font="Comic Sans MS" border="full" textIndent="left"></tableRow>
</table>
<table>
<tableRow text="XIOQDURVCT" font="Comic Sans MS" border="none" textIndent="right"></tableRow>
<tableRow text="DRFVPFLKEF" font="Comic Sans MS" border="none" textIndent="right"></tableRow>
<tableRow text="SQNOCODDCL" font="Comic Sans MS" border="none" textIndent="right"></tableRow>
<tableRow text="TSAUXXDKRK" font="Comic Sans MS" border="none" textIndent="right"></tableRow>
<tableRow text="ELFQKEIWCD" font="Comic Sans MS" border="none" textIndent="right"></tableRow>
<tableRow text="TPJGOZIENY" font="Comic Sans MS" border="none" textIndent="right"></tableRow>
<tableRow text="PLEELEAZMC" font="Comic Sans MS" border="none" textIndent="right"></tableRow>
<tableRow text="IHLZSNLPGC" font="Comic Sans MS" border="none" textIndent="right"></tableRow>
<tableRow text="JKYEWUVDUY" font="Comic Sans MS" border="none" textIndent="right"></tableRow>
<tableRow text="WTNIIUDNOF" font="Comic Sans MS" border="none" textIndent="right"></tableRow>
<tableRow text="XOGHVIMDIC" font="Comic Sans MS" border="none" textIndent="right"></tableRow>
<tableRow text="WSVOUGQETR" font="Comic Sans MS" border="none" textIndent="right"></tableRow>
<tableRow text="GTQHDPOMIB" font="Comic Sans MS" border="none" textIndent="right"></tableRow>
<tableRow text="WVHUEIJETP" font="Comic Sans MS" border="none" textIndent="right"></tableRow>
<tableRow text="BKGLMBELUX" font="Comic Sans MS" border="none" textIndent="right"></tableRow>
<tableRow text="SUWAMZIZQC" font="Comic Sans MS" border="none" textIndent="right"></tableRow>
<tableRow text="XGGYDBTDWM" font="Comic Sans MS" border="none" textIndent="right"></tableRow>
<tableRow text="XBJSRQNVJS" font="Comic Sans MS" border="none" textIndent="right"></tableRow>
<tableRow text="CELWXJDWRQ" font="Comic Sans MS" border="none" textIndent="right"></tableRow>
</table>
<table>
<tableRow text="AFSYOFKWUJ" font="Arial" border="row" textIndent="center"></tableRow>
<tableRow text="NNHILKLYLR" font="Arial" border="row" textIndent="center"></tableRow>
<tableRow text="ZHPSRVOSMD" font="Arial" border="row" textIndent="center"></tableRow>
<tableRow text="LBQHQREXDO" font="Arial" border="row" textIndent="center"></tableRow>
<tableRow text="YTNKDZOWXX" font="Arial" border="row" textIndent="center"></tableRow>
<tableRow text="IFLKKSDKOB" font="Arial" border="row" textIndent="center"></tableRow>
<tableRow text="DSTJHDFHDL" font="Arial" border="row" textIndent="center"></tableRow>
<tableRow text="SSKOIPXZRK" font="Arial" border="row" textIndent="center"></tableRow>
<tableRow text="NNEWRBDGOL" font="Arial" border="row" textIndent="center"></tableRow>
<tableRow text="HUHAIIRNQY" font="Arial" border="row" textIndent="center"></tableRow>
<tableRow text="CASRKPKGSB" font="Arial" border="row" textIndent="center"></tableRow>
</table>
<table>
<tableRow text="LXHDBTGNCW" font="Times New Roman" border="full" textIndent="right"></tableRow>
<tableRow text="VCMSQIMHQJ" font="Times New Roman" border="full" textIndent="right"></tableRow>
<tableRow text="LTHDVYHCVN" font="Times New Roman" border="full" textIndent="right"></tableRow>
<tableRow text="PIDOCWWIKF" font="Times New Roman" border="full" textIndent="right"></tableRow>
<tableRow text="OQLIPOEKQT" font="Times New Roman" border="full" textIndent="right"></tableRow>
<tableRow text="FYDPAQWVWJ" font="Times New Roman" border="full" textIndent="right"></tableRow>
<tableRow text="QGOSPQOKJE" font="Times New Roman" border="full" textIndent="right"></tableRow>
<tableRow text="UGTRAIMHGS" font="Times New Roman" border="full" textIndent="right"></tableRow>
<tableRow text="OZUJDFEDZN" font="Times New Roman" border="full" textIndent="right"></tableRow>
<tableRow text="PXIDGPWFIO" font="Times New Roman" border="full" textIndent="right"></tableRow>
<tableRow text="BVCKSEOCYU" font="Times New Roman" border="full" textIndent="right"></tableRow>
<tableRow text="CZJIGEBAJA" font="Times New Roman" border="full" textIndent="right"></tableRow>
<tableRow text="OFPLMEYXTL" font="Times New Roman" border="full" textIndent="right"></tableRow>
</table>
<table>
<tableRow text="MAMPKEYAWI" font="Comic Sans MS" border="full" textIndent="right"></tableRow>
<tableRow text="ICABXWBHMC" font="Comic Sans MS" border="full" textIndent="right"></tableRow>
<tableRow text="ZHCZCIQDHG" font="Comic Sans MS" border="full" textIndent="right"></tableRow>
<tableRow text="LOTVWMNGVO" font="Comic Sans MS" border="full" textIndent="right"></tableRow>
<tableRow text="MGLPPAGNUL" font="Comic Sans MS" border="full" textIndent="right"></tableRow>
<tableRow text="VVCHEHNDDF" font="Comic Sans MS" border="full" textIndent="right"></tableRow>
<tableRow text="LGOQJIYRQE" font="Comic Sans MS" border="full" textIndent="right"></tableRow>
<tableRow text="KSWVJSAFMT" font="Comic Sans MS" border="full" textIndent="right"></tableRow>
<tableRow text="GJKTIHPNSB" font="Comic Sans MS" border="full" textIndent="right"></tableRow>
<tableRow text="UEAPORENLN" font="Comic Sans MS" border="full" textIndent="right"></tableRow>
<tableRow text="UZPJQNNYSC" font="Comic Sans MS" border="full" textIndent="right"></tableRow>
<tableRow text="LAJMXIBPHQ" font="Comic Sans MS" border="full" textIndent="right"></tableRow>
<tableRow text="KSYCWRFWYZ" font="Comic Sans MS" border="full" textIndent="right"></tableRow>
<tableRow text="IJTUOOGXPS" font="Comic Sans MS" border="full" textIndent="right"></tableRow>
<tableRow text="LCZIYKPVWT" font="Comic Sans MS" border="full" textIndent="right"></tableRow>
<tableRow text="CXRDFWSYDV" font="Comic Sans MS" border="full" textIndent="right"></tableRow>
</table>
<table>
<tableRow text="YKOHWBSFVP" font="Arial" border="column" textIndent="left"></tableRow>
<tableRow text="GNVVSVFPXQ" font="Arial" border="column" textIndent="left"></tableRow>
<tableRow text="WDGQSYAIVM" font="Arial" border="column" textIndent="left"></tableRow>
<tableRow text="MKOGIZBWNR" font="Arial" border="column" textIndent="left"></tableRow>
<tableRow text="HROFDKLALI" font="Arial" border="column" textIndent="left"></tableRow>
<tableRow text="LGWYIACNYA" font="Arial" border="column" textIndent="left"></tableRow>
</table>
<table>
<tableRow text="IAEQKFTGXT" font="Comic Sans MS" border="none" textIndent="right"></tableRow>
<tableRow text="EMVMHTAUVL" font="Comic Sans MS" border="none" textIndent="right"></tableRow>
<tableRow text="ZWABGOGDDV" font="Comic Sans MS" border="none" textIndent="right"></tableRow>
<tableRow text="ADKQXYHHAU" font="Comic Sans MS" border="none" textIndent="right"></tableRow>
<tableRow text="NAPAICURJA" font="Comic Sans MS" border="none" textIndent="right"></tableRow>
<tableRow text="NJAMFCRYRM" font="Comic Sans MS" border="none" textIndent="right"></tableRow>
</table>
<table>
<tableRow text="LGGAZSPVTZ" font="Arial" border="row" textIndent="right"></tableRow>
<tableRow text="WZMJBOGCTT" font="Arial" border="row" textIndent="right"></tableRow>
<tableRow text="HCRNMBFTFF" font="Arial" border="row" textIndent="right"></tableRow>
<tableRow text="IDAPDNJXGK" font="Arial" border="row" textIndent="right"></tableRow>
<tableRow text="CVNZENFXKN" font="Arial" border="row" textIndent="right"></tableRow>
<tableRow text="SSXLWXLUNK" font="Arial" border="row" textIndent="right"></tableRow>
<tableRow text="WHYQHDELTN" font="Arial" border="row" textIndent="right"></tableRow>
<tableRow text="FTMONVRZNM" font="Arial" border="row" textIndent="right"></tableRow>
<tableRow text="QLMOYJWKIP" font="Arial" border="row" textIndent="right"></tableRow>
<tableRow text="UKLTAECTOG" font="Arial" border="row" textIndent="right"></tableRow>
</table>
<table>
<tableRow text="UFVRFVQHHE" font="Times New Roman" border="full" textIndent="right"></tableRow>
<tableRow text="MQKIZQXNVK" font="Times New Roman" border="full" textIndent="right"></tableRow>
<tableRow text="HBZFZNSYTT" font="Times New Roman" border="full" textIndent="right"></tableRow>
</table>
<table>
<tableRow text="ANVNYHLTNQ" font="Arial" border="none" textIndent="right"></tableRow>
<tableRow text="VTECENCJPZ" font="Arial" border="none" textIndent="right"></tableRow>
<tableRow text="CQGTPYQPLL" font="Arial" border="none" textIndent="right"></tableRow>
<tableRow text="VKAPXXLYQR" font="Arial" border="none" textIndent="right"></tableRow>
<tableRow text="FTTKJXTVYM" font="Arial" border="none" textIndent="right"></tableRow>
<tableRow text="WBZPORYAEZ" font="Arial" border="none" textIndent="right"></tableRow>
<tableRow text="GSKAYLSPLX" font="Arial" border="none" textIndent="right"></tableRow>
<tableRow text="RWYRRXPXPF" font="Arial" border="none" textIndent="right"></tableRow>
<tableRow text="IGBLWGHMTZ" font="Arial" border="none" textIndent="right"></tableRow>
<tableRow text="YHANSOHVVJ" font="Arial" border="none" textIndent="right"></tableRow>
<tableRow text="BUQWWUCIIR" font="Arial" border="none" textIndent="right"></tableRow>
<tableRow text="VRGEXPIEQF" font="Arial" border="none" textIndent="right"></tableRow>
<tableRow text="YJFMPSXQKX" font="Arial" border="none" textIndent="right"></tableRow>
<tableRow text="SGTWBERZZV" font="Arial" border="none" textIndent="right"></tableRow>
</table>
<table>
<tableRow text="SXIOJBRDHK" font="Arial" border="column" textIndent="center"></tableRow>
<tableRow text="HDZYUHFMYH" font="Arial" border="column" textIndent="center"></tableRow>
<tableRow text="KJBGJGJHWN" font="Arial" border="column" textIndent="center"></tableRow>
<tableRow text="ZRXMPLNJIU" font="Arial" border="column" textIndent="center"></tableRow>
<tableRow text="KEZPWRHPOX" font="Arial" border="column" textIndent="center"></tableRow>
<tableRow text="OWCEQVPGFQ" font="Arial" border="column" textIndent="center"></tableRow>
<tableRow text="BFOBETEMLE" font="Arial" border="column" textIndent="center"></tableRow>
<tableRow text="DUHANDZETE" font="Arial" border="column" textIndent="center"></tableRow>
<tableRow text="ZMTVYXVTAS" font="Arial" border="column" textIndent="center"></tableRow>
<tableRow text="LZBAFVPXVP" font="Arial" border="column" textIndent="center"></tableRow>
<tableRow text="YCPZGHBNCF" font="Arial" border="column" textIndent="center"></tableRow>
<tableRow text="EDIVPYCTZF" font="Arial" border="column" textIndent="center"></tableRow>
<tableRow text="ZGZEVFYFRW" font="Arial" border="column" textIndent="center"></tableRow>
<tableRow text="UMGLXYAZXJ" font="Arial" border="column" textIndent="center"></tableRow>
<tableRow text="RXWTFYUOLU" font="Arial" border="column" textIndent="center"></tableRow>
<tableRow text="MHUHYZKJWI" font="Arial" border="column" textIndent="center"></tableRow>
</table>
<table>
<tableRow text="RDQJWUASCH" font="Comic Sans MS" border="none" textIndent="right"></tableRow>
<tableRow text="YLGQSXZTJG" font="Comic Sans MS" border="none" textIndent="right"></tableRow>
<tableRow text="MYGNMFRNFO" font="Comic Sans MS" border="none" textIndent="right"></tableRow>
<tableRow text="ECNSFALFGX" font="Comic Sans MS" border="none" textIndent="right"></tableRow>
<tableRow text="OBYYIBCGDE" font="Comic Sans MS" border="none" textIndent="right"></tableRow>
<tableRow text="QBMWHMBUBJ" font="Comic Sans MS" border="none" textIndent="right"></tableRow>
<tableRow text="FMEVRASZBT" font="Comic Sans MS" border="none" textIndent="right"></tableRow>
</table>
<table>
<tableRow text="UGDENFPYTN" font="Comic Sans MS" border="full" textIndent="right"></tableRow>
<tableRow text="XEZDPLCEXO" font="Comic Sans MS" border="full" textIndent="right"></tableRow>
<tableRow text="GDAFAJHZRB" font="Comic Sans MS" border="full" textIndent="right"></tableRow>
<tableRow text="GCOHAWKHHV" font="Comic Sans MS" border="full" textIndent="right"></tableRow>
<tableRow text="UIQCJOVQIG" font="Comic Sans MS" border="full" textIndent="right"></tableRow>
<tableRow text="HFXHKTVOMG" font="Comic Sans MS" border="full" textIndent="right"></tableRow>
<tableRow text="FFLQMIFVRB" font="Comic Sans MS" border="full" textIndent="right"></tableRow>
<tableRow text="GTJEORPSZN" font="Comic Sans MS" border="full" textIndent="right"></tableRow>
</table>
<table>
<tableRow text="AJSZKVHZFZ" font="Arial" border="column" textIndent="right"></tableRow>
<tableRow text="SRGYDDAPKT" font="Arial" border="column" textIndent="right"></tableRow>
<tableRow text="RGNGAGAHUI" font="Arial" border="column" textIndent="right"></tableRow>
<tableRow text="FIITEAHTOB" font="Arial" border="column" textIndent="right"></tableRow>
</table>
<table>
<tableRow text="EZIZOJORBX" font="Arial" border="none" textIndent="right"></tableRow>
<tableRow text="LHOOIOQNKL" font="Arial" border="none" textIndent="right"></tableRow>
<tableRow text="LATJSSECOF" font="Arial" border="none" textIndent="right"></tableRow>
<tableRow text="HUMKGFXPPN" font="Arial" border="none" textIndent="right"></tableRow>
</table>
<table>
<tableRow text="DTVBKYSILW" font="Comic Sans MS" border="full" textIndent="right"></tableRow>
<tableRow text="GHRHKSUVYN" font="Comic Sans MS" border="full" textIndent="right"></tableRow>
<tableRow text="YNCZGXVYOY" font="Comic Sans MS" border="full" textIndent="right"></tableRow>
<tableRow text="JFYQLYEAID" font="Comic Sans MS" border="full" textIndent="right"></tableRow>
<tableRow text="GLMQPGAWCH" font="Comic Sans MS" border="full" textIndent="right"></tableRow>
<tableRow text="ZQAUSWKXYK" font="Comic Sans MS" border="full" textIndent="right"></tableRow>
<tableRow text="YPZVETURMF" font="Comic Sans MS" border="full" textIndent="right"></tableRow>
<tableRow text="RCZHSEOWVP" font="Comic Sans MS" border="full" textIndent="right"></tableRow>
<tableRow text="ZHCZBUWSFH" font="Comic Sans MS" border="full" textIndent="right"></tableRow>
<tableRow text="ZTQSJCQUTA" font="Comic Sans MS" border="full" textIndent="right"></tableRow>
<tableRow text="YSVELZMYJJ" font="Comic Sans MS" border="full" textIndent="right"></tableRow>
<tableRow text="CXCMZLZYJO" font="Comic Sans MS" border="full" textIndent="right"></tableRow>
<tableRow text="JZWEAJYAFD" font="Comic Sans MS" border="full" textIndent="right"></tableRow>
<tableRow text="BJENAWPTZX" font="Comic Sans MS" border="full" textIndent="right"></tableRow>
</table>
<table>
<tableRow text="ENOGJHYLMA" font="Times New Roman" border="full" textIndent="right"></tableRow>
<tableRow text="ZDCRRETDMY" font="Times New Roman" border="full" textIndent="right"></tableRow>
<tableRow text="UZRROEQXFW" font="Times New Roman" border="full" textIndent="right"></tableRow>
<tableRow text="HHXSHKGSDN" font="Times New Roman" border="full" textIndent="right"></tableRow>
<tableRow text="NROEXCSAPC" font="Times New Roman" border="full" textIndent="right"></tableRow>
<tableRow text="CYMUFNAVSN" font="Times New Roman" border="full" textIndent="right"></tableRow>
</table>
<table>
<tableRow text="OGAQGGEUCK" font="Arial" border="none" textIndent="center"></tableRow>
<tableRow text="RJLYYMRMLT" font="Arial" border="none" textIndent="center"></tableRow>
<tableRow text="QWTCIMGYQA" font="Arial" border="none" textIndent="center"></tableRow>
<tableRow text="BTUJZNLDRN" font="Arial" border="none" textIndent="center"></tableRow>
</table>
<table>
<tableRow text="MWHVWKAHCQ" font="Comic Sans MS" border="none" textIndent="left"></tableRow>
<tableRow text="VMYSLDNFPA" font="Comic Sans MS" border="none" textIndent="left"></tableRow>
<tableRow text="JRNTGXDDGI" font="Comic Sans MS" border="none" textIndent="left"></tableRow>
<tableRow text="UOJOOMFERN" font="Comic Sans MS" border="none" textIndent="left"></tableRow>
<tableRow text="BPWGXBPCFO" font="Comic Sans MS" border="none" textIndent="left"></tableRow>
<tableRow text="FUMJARQYPR" font="Comic Sans MS" border="none" textIndent="left"></tableRow>
<tableRow text="DYQXVMBBWA" font="Comic Sans MS" border="none" textIndent="left"></tableRow>
</table>
<table>
<tableRow text="SCJRIWXQQZ" font="Comic Sans MS" border="none" textIndent="center"></tableRow>
<tableRow text="KFAIPCTZNF" font="Comic Sans MS" border="none" textIndent="center"></tableRow>
<tableRow text="OEKNVXVNWY" font="Comic Sans MS" border="none" textIndent="center"></tableRow>
<tableRow text="JYKSFKARUW" font="Comic Sans MS" border="none" textIndent="center"></tableRow>
<tableRow text="GSSMEOHDPT" font="Comic Sans MS" border="none" textIndent="center"></tableRow>
<tableRow text="TNHOUNWPVK" font="Comic Sans MS" border="none" textIndent="center"></tableRow>
<tableRow text="KRULPQOXXR" font="Comic Sans MS" border="none" textIndent="center"></tableRow>
<tableRow text="NFWJQFISPS" font="Comic Sans MS" border="none" textIndent="center"></tableRow>
<tableRow text="TQEKHPRJKM" font="Comic Sans MS" border="none" textIndent="center"></tableRow>
<tableRow text="TNDPPPVMJE" font="Comic Sans MS" border="none" textIndent="center"></tableRow>
<tableRow text="GJWSNNEEXU" font="Comic Sans MS" border="none" textIndent="center"></tableRow>
</table>
<table>
<tableRow text="EICMMFJAIH" font="Arial" border="full" textIndent="center"></tableRow>
<tableRow text="WMQCCKFCTP" font="Arial" border="full" textIndent="center"></tableRow>
<tableRow text="FQQSBZSGKY" font="Arial" border="full" textIndent="center"></tableRow>
<tableRow text="NPTQUDASQF" font="Arial" border="full" textIndent="center"></tableRow>
<tableRow text="TWBXLXAODQ" font="Arial" border="full" textIndent="center"></tableRow>
<tableRow text="FKVPNLGCLL" font="Arial" border="full" textIndent="center"></tableRow>
<tableRow text="KQEOOCXVOR" font="Arial" border="full" textIndent="center"></tableRow>
<tableRow text="QPSVALYZVO" font="Arial" border="full" textIndent="center"></tableRow>
<tableRow text="TQWAUYAFPI" font="Arial" border="full" textIndent="center"></tableRow>
<tableRow text="IBEKZGRFQJ" font="Arial" border="full" textIndent="center"></tableRow>
<tableRow text="RBLZKLUTOL" font="Arial" border="full" textIndent="center"></tableRow>
<tableRow text="DEIXYHPKKE" font="Arial" border="full" textIndent="center"></tableRow>
<tableRow text="BKGKBWCJUN" font="Arial" border="full" textIndent="center"></tableRow>
<tableRow text="KJLNLLMZJW" font="Arial" border="full" textIndent="center"></tableRow>
<tableRow text="TPSUSJGDNP" font="Arial" border="full" textIndent="center"></tableRow>
<tableRow text="EHUNKYFHID" font="Arial" border="full" textIndent="center"></tableRow>
</table>
<table>
<tableRow text="THYYUBLZJI" font="Arial" border="column" textIndent="center"></tableRow>
<tableRow text="HIHKGPZRHQ" font="Arial" border="column" textIndent="center"></tableRow>
<tableRow text="KRQZFMUTEG" font="Arial" border="column" textIndent="center"></tableRow>
<tableRow text="RKHDMTBLJE" font="Arial" border="column" textIndent="center"></tableRow>
<tableRow text="EBWVCOCEWA" font="Arial" border="column" textIndent="center"></tableRow>
<tableRow text="JBJDHXLUZQ" font="Arial" border="column" textIndent="center"></tableRow>
<tableRow text="DGSEJKEIPE" font="Arial" border="column" textIndent="center"></tableRow>
<tableRow text="UUTVHXGTFT" font="Arial" border="column" textIndent="center"></tableRow>
<tableRow text="HGYFAPHJCD" font="Arial" border="column" textIndent="center"></tableRow>
</table>
<table>
<tableRow text="HGZVFZMTBN" font="Comic Sans MS" border="none" textIndent="right"></tableRow>
<tableRow text="CSSULNFCMD" font="Comic Sans MS" border="none" textIndent="right"></tableRow>
<tableRow text="XIVOUEPPQG" font="Comic Sans MS" border="none" textIndent="right"></tableRow>
</table>
<table>
<tableRow text="JWNSGPEYBZ" font="Arial" border="row" textIndent="center"></tableRow>
<tableRow text="OBVMSWTING" font="Arial" border="row" textIndent="center"></tableRow>
<tableRow text="BIEEGZITTO" font="Arial" border="row" textIndent="center"></tableRow>
<tableRow text="CSEHPTNYPP" font="Arial" border="row" textIndent="center"></tableRow>
<tableRow text="CQWJMLHVWO" font="Arial" border="row" textIndent="center"></tableRow>
<tableRow text="TDBIVSPAKF" font="Arial" border="row" textIndent="center"></tableRow>
<tableRow text="HJYTMCGNAF" font="Arial" border="row" textIndent="center"></tableRow>
<tableRow text="TVEQGENUJA" font="Arial" border="row" textIndent="center"></tableRow>
<tableRow text="ZWKAHPEOEL" font="Arial" border="row" textIndent="center"></tableRow>
<tableRow text="MXJVYGMIZR" font="Arial" border="row" textIndent="center"></tableRow>
<tableRow text="ZHIUYXYAVU" font="Arial" border="row" textIndent="center"></tableRow>
<tableRow text="FRUBFXXHEH" font="Arial" border="row" textIndent="center"></tableRow>
<tableRow text="ZYYNLWKPPZ" font="Arial" border="row" textIndent="center"></tableRow>
</table>
<table>
<tableRow text="ZZCCVUJPOA" font="Comic Sans MS" border="none" textIndent="right"></tableRow>
</table>
<table>
<tableRow text="POJYIBPEQL" font="Arial" border="full" textIndent="left"></tableRow>
<tableRow text="ARLRIQJVRT" font="Arial" border="full" textIndent="left"></tableRow>
</table>
<table>
<tableRow text="GRKXRAHYNI" font="Times New Roman" border="full" textIndent="center"></tableRow>
<tableRow text="WJBAGNFZVK" font="Times New Roman" border="full" textIndent="center"></tableRow>
<tableRow text="QULBXJNEQP" font="Times New Roman" border="full" textIndent="center"></tableRow>
<tableRow text="JXUZEMOQVQ" font="Times New Roman" border="full" textIndent="center"></tableRow>
<tableRow text="JDQVUYRSYZ" font="Times New Roman" border="full" textIndent="center"></tableRow>
<tableRow text="BVTODPQLED" font="Times New Roman" border="full" textIndent="center"></tableRow>
<tableRow text="XNXLJCPMVN" font="Times New Roman" border="full" textIndent="center"></tableRow>
<tableRow text="RCIRSXXATY" font="Times New Roman" border="full" textIndent="center"></tableRow>
<tableRow text="OXTKKZVRGX" font="Times New Roman" border="full" textIndent="center"></tableRow>
<tableRow text="TNYUMUIYIA" font="Times New Roman" border="full" textIndent="center"></tableRow>
<tableRow text="OQCYOCZIOV" font="Times New Roman" border="full" textIndent="center"></tableRow>
<tableRow text="PLHTQWVMHV" font="Times New Roman" border="full" textIndent="center"></tableRow>
<tableRow text="PXFYHXBHKH" font="Times New Roman" border="full" textIndent="center"></tableRow>
<tableRow text="CMEJEHNVIA" font="Times New Roman" border="full" textIndent="center"></tableRow>
<tableRow text="KUPBKIYEMQ" font="Times New Roman" border="full" textIndent="center"></tableRow>
</table>
<table>
<tableRow text="ZRCQCTPIRT" font="Arial" border="full" textIndent="right"></tableRow>
<tableRow text="RXKYASUTBG" font="Arial" border="full" textIndent="right"></tableRow>
<tableRow text="KKQEOZIVMX" font="Arial" border="full" textIndent="right"></tableRow>
<tableRow text="LPOENYIVAF" font="Arial" border="full" textIndent="right"></tableRow>
<tableRow text="JLENYWEEMF" font="Arial" border="full" textIndent="right"></tableRow>
<tableRow text="SUHAYPCYAN" font="Arial" border="full" textIndent="right"></tableRow>
<tableRow text="LHCKVJZZGT" font="Arial" border="full" textIndent="right"></tableRow>
<tableRow text="QOPLGBCDML" font="Arial" border="full" textIndent="right"></tableRow>
<tableRow text="FMQDKKOJTM" font="Arial" border="full" textIndent="right"></tableRow>
<tableRow text="VDJOEFDLPP" font="Arial" border="full" textIndent="right"></tableRow>
<tableRow text="QTJTDDTRUW" font="Arial" border="full" textIndent="right"></tableRow>
<tableRow text="WDUIWERYTH" font="Arial" border="full" textIndent="right"></tableRow>
</table>
<table>
<tableRow text="VVJQETXORD" font="Comic Sans MS" border="full" textIndent="right"></tableRow>
<tableRow text="ETXDVHPQXW" font="Comic Sans MS" border="full" textIndent="right"></tableRow>
<tableRow text="ZPKZNQLKJZ" font="Comic Sans MS" border="full" textIndent="right"></tableRow>
<tableRow text="ZVLJXDJNTP" font="Comic Sans MS" border="full" textIndent="right"></tableRow>
<tableRow text="IHGATROFIZ" font="Comic Sans MS" border="full" textIndent="right"></tableRow>
<tableRow text="BMWLQGKTMQ" font="Comic Sans MS" border="full" textIndent="right"></tableRow>
<tableRow text="OFIOMLSCPN" font="Comic Sans MS" border="full" textIndent="right"></tableRow>
<tableRow text="WYPXFVGJUB" font="Comic Sans MS" border="full" textIndent="right"></tableRow>
<tableRow text="SQLELSAEDX" font="Comic Sans MS" border="full" textIndent="right"></tableRow>
<tableRow text="NEWFRKXUPS" font="Comic Sans MS" border="full" textIndent="right"></tableRow>
<tableRow text="SONQULMIUI" font="Comic Sans MS" border="full" textIndent="right"></tableRow>
<tableRow text="DRXQEXLIHT" font="Comic Sans MS" border="full" textIndent="right"></tableRow>
<tableRow text="ZTUHURVOMM" font="Comic Sans MS" border="full" textIndent="right"></tableRow>
<tableRow text="FLLJSIWHYW" font="Comic Sans MS" border="full" textIndent="right"></tableRow>
<tableRow text="XAGEUXLHQQ" font="Comic Sans MS" border="full" textIndent="right"></tableRow>
<tableRow text="FQLXWETTDB" font="Comic Sans MS" border="full" textIndent="right"></tableRow>
<tableRow text="HIIJNKARNY" font="Comic Sans MS" border="full" textIndent="right"></tableRow>
<tableRow text="BUJQNOUQRL" font="Comic Sans MS" border="full" textIndent="right"></tableRow>
<tableRow text="QMVNYZDCBJ" font="Comic Sans MS" border="full" textIndent="right"></tableRow>
</table>
<table>
<tableRow text="RTLLBMHDDP" font="Gotham" border="full" textIndent="center"></tableRow>
<tableRow text="XEWPULQWIH" font="Gotham" border="full" textIndent="center"></tableRow>
<tableRow text="LEOBIFWJSX" font="Gotham" border="full" textIndent="center"></tableRow>
<tableRow text="VYYUVFVHPH" font="Gotham" border="full" textIndent="center"></tableRow>
<tableRow text="NXLMJDBLYM" font="Gotham" border="full" textIndent="center"></tableRow>
<tableRow text="CDMXKSHTJX" font="Gotham" border="full" textIndent="center"></tableRow>
<tableRow text="TLXVQMQDEW" font="Gotham" border="full" textIndent="center"></tableRow>
<tableRow text="KAUPJTZRKZ" font="Gotham" border="full" textIndent="center"></tableRow>
<tableRow text="HWRAIRWSOE" font="Gotham" border="full" textIndent="center"></tableRow>
<tableRow text="YXERGZHYVE" font="Gotham" border="full" textIndent="center"></tableRow>
<tableRow text="WSOHVKUCGV" font="Gotham" border="full" textIndent="center"></tableRow>
<tableRow text="FPZRORKRUW" font="Gotham" border="full" textIndent="center"></tableRow>
<tableRow text="EKSCBNFFDF" font="Gotham" border="full" textIndent="center"></tableRow>
<tableRow text="EGLGLAQEGO" font="Gotham" border="full" textIndent="center"></tableRow>
<tableRow text="FRQLKHMZOE" font="Gotham" border="full" textIndent="center"></tableRow>
<tableRow text="WZAJVHZHNC" font="Gotham" border="full" textIndent="center"></tableRow>
<tableRow text="HHWKLCGLWI" font="Gotham" border="full" textIndent="center"></tableRow>
</table>
<table>
<tableRow text="AQHXXIBXVG" font="Comic Sans MS" border="none" textIndent="left"></tableRow>
</table>
<table>
<tableRow text="XYSMBKIUJO" font="Arial" border="row" textIndent="left"></tableRow>
<tableRow text="BRUKCNZSAV" font="Arial" border="row" textIndent="left"></tableRow>
<tableRow text="FCHRRWNWWF" font="Arial" border="row" textIndent="left"></tableRow>
<tableRow text="VWMXCYKVAN" font="Arial" border="row" textIndent="left"></tableRow>
<tableRow text="PPKHHNSTDO" font="Arial" border="row" textIndent="left"></tableRow>
<tableRow text="RTTXUVZUGA" font="Arial" border="row" textIndent="left"></tableRow>
</table>
<table>
<tableRow text="NVPFRYOBUR" font="Arial" border="none" textIndent="right"></tableRow>
<tableRow text="CQHHFEQJUO" font="Arial" border="none" textIndent="right"></tableRow>
<tableRow text="SWFTZHMYJK" font="Arial" border="none" textIndent="right"></tableRow>
<tableRow text="ZQTJVJFFCI" font="Arial" border="none" textIndent="right"></tableRow>
<tableRow text="XPJZOGFVMN" font="Arial" border="none" textIndent="right"></tableRow>
<tableRow text="ZQRWUNNWCG" font="Arial" border="none" textIndent="right"></tableRow>
<tableRow text="CECJCZGKKL" font="Arial" border="none" textIndent="right"></tableRow>
<tableRow text="ZCWWWPJKIQ" font="Arial" border="none" textIndent="right"></tableRow>
<tableRow text="ETRJDMOQEL" font="Arial" border="none" textIndent="right"></tableRow>
<tableRow text="EFRMUWCXKE" font="Arial" border="none" textIndent="right"></tableRow>
<tableRow text="CZOTTWWJFH" font="Arial" border="none" textIndent="right"></tableRow>
<tableRow text="TBRIPLMKPQ" font="Arial" border="none" textIndent="right"></tableRow>
<tableRow text="ZQZHASKIPX" font="Arial" border="none" textIndent="right"></tableRow>
</table>
<table>
<tableRow text="UJOVLVBMDZ" font="Comic Sans MS" border="none" textIndent="right"></tableRow>
<tableRow text="LNELDIIKOU" font="Comic Sans MS" border="none" textIndent="right"></tableRow>
<tableRow text="DJNEHJLQXZ" font="Comic Sans MS" border="none" textIndent="right"></tableRow>
<tableRow text="ZOHCABTGAU" font="Comic Sans MS" border="none" textIndent="right"></tableRow>
<tableRow text="OYUKHSKSQU" font="Comic Sans MS" border="none" textIndent="right"></tableRow>
<tableRow text="QBQTAPFLCU" font="Comic Sans MS" border="none" textIndent="right"></tableRow>
</table>
<table>
<tableRow text="ULBSDAPCBW" font="Arial" border="column" textIndent="center"></tableRow>
<tableRow text="WWHNLHOWCP" font="Arial" border="column" textIndent="center"></tableRow>
<tableRow text="IOYGNZQJYN" font="Arial" border="column" textIndent="center"></tableRow>
</table>
<table>
<tableRow text="ZOYWXWCARR" font="Comic Sans MS" border="none" textIndent="right"></tableRow>
<tableRow text="WABJMRNOGM" font="Comic Sans MS" border="none" textIndent="right"></tableRow>
<tableRow text="NKQXGTIZHS" font="Comic Sans MS" border="none" textIndent="right"></tableRow>
<tableRow text="LSUGZKUSRZ" font="Comic Sans MS" border="none" textIndent="right"></tableRow>
<tableRow text="NDUKGIGUBB" font="Comic Sans MS" border="none" textIndent="right"></tableRow>
<tableRow text="NKUMGJJMTR" font="Comic Sans MS" border="none" textIndent="right"></tableRow>
<tableRow text="TJMCHRLUUD" font="Comic Sans MS" border="none" textIndent="right"></tableRow>
<tableRow text="HREYOAKKPE" font="Comic Sans MS" border="none" textIndent="right"></tableRow>
</table>
<table>
<tableRow text="QJUNYDOJQJ" font="Gotham" border="full" textIndent="center"></tableRow>
<tableRow text="LGXQIMNIGL" font="Gotham" border="full" textIndent="center"></tableRow>
<tableRow text="ITQUSTZPUA" font="Gotham" border="full" textIndent="center"></tableRow>
<tableRow text="XUNPLRHZKS" font="Gotham" border="full" textIndent="center"></tableRow>
<tableRow text="UQCZZAGBSN" font="Gotham" border="full" textIndent="center"></tableRow>
<tableRow text="HXXPUOJUPZ" font="Gotham" border="full" textIndent="center"></tableRow>
<tableRow text="RHHWBNTBEZ" font="Gotham" border="full" textIndent="center"></tableRow>
</table>
<table>
<tableRow text="XNEXMUZVOX" font="Arial" border="column" textIndent="left"></tableRow>
<tableRow text="TSIGEIJUHC" font="Arial" border="column" textIndent="left"></tableRow>
<tableRow text="ZHQNSEMCRU" font="Arial" border="column" textIndent="left"></tableRow>
<tableRow text="LWUTIUZPEC" font="Arial" border="column" textIndent="left"></tableRow>
<tableRow text="KAINULNLIA" font="Arial" border="column" textIndent="left"></tableRow>
<tableRow text="PXZBZYISXS" font="Arial" border="column" textIndent="left"></tableRow>
<tableRow text="NTLJMDKPOG" font="Arial" border="column" textIndent="left"></tableRow>
<tableRow text="QBXQEHQYPN" font="Arial" border="column" textIndent="left"></tableRow>
<tableRow text="YJESIVBTKX" font="Arial" border="column" textIndent="left"></tableRow>
</table>
<table>
<tableRow text="TFCWFGCIUY" font="Times New Roman" border="full" textIndent="left"></tableRow>
<tableRow text="QGWEFIPIUH" font="Times New Roman" border="full" textIndent="left"></tableRow>
<tableRow text="AJFRBBBTSV" font="Times New Roman" border="full" textIndent="left"></tableRow>
<tableRow text="YCRVCQVKVJ" font="Times New Roman" border="full" textIndent="left"></tableRow>
<tableRow text="JYWDMJHDYR" font="Times New Roman" border="full" textIndent="left"></tableRow>
<tableRow text="TDHDGJXFPG" font="Times New Roman" border="full" textIndent="left"></tableRow>
<tableRow text="OQLCGDRVKP" font="Times New Roman" border="full" textIndent="left"></tableRow>
</table>
<table>
<tableRow text="YGWMWFGUMR" font="Arial" border="column" textIndent="center"></tableRow>
<tableRow text="UXFFGASXGL" font="Arial" border="column" textIndent="center"></tableRow>
<tableRow text="LVHUJEYDFI" font="Arial" border="column" textIndent="center"></tableRow>
<tableRow text="APNWUDGDMF" font="Arial" border="column" textIndent="center"></tableRow>
<tableRow text="IVMCNTDQPG" font="Arial" border="column" textIndent="center"></tableRow>
<tableRow text="QHYFEVAVMH" font="Arial" border="column" textIndent="center"></tableRow>
<tableRow text="FLAVERTAAH" font="Arial" border="column" textIndent="center"></tableRow>
<tableRow text="EDYKYAQEGI" font="Arial" border="column" textIndent="center"></tableRow>
<tableRow text="LIVRPORTJK" font="Arial" border="column" textIndent="center"></tableRow>
<tableRow text="HPTRZRRIRF" font="Arial" border="column" textIndent="center"></tableRow>
<tableRow text="FGINTNDQIG" font="Arial" border="column" textIndent="center"></tableRow>
</table>
<table>
<tableRow text="CSVIOFPPWN" font="Comic Sans MS" border="none" textIndent="left"></tableRow>
<tableRow text="FHZGYVGTKP" font="Comic Sans MS" border="none" textIndent="left"></tableRow>
<tableRow text="CHXVLJFAQC" font="Comic Sans MS" border="none" textIndent="left"></tableRow>
<tableRow text="DNPVCMUDAR" font="Comic Sans MS" border="none" textIndent="left"></tableRow>
<tableRow text="RSBWZLKJBZ" font="Comic Sans MS" border="none" textIndent="left"></tableRow>
<tableRow text="JWBOORUHVX" font="Comic Sans MS" border="none" textIndent="left"></tableRow>
<tableRow text="RBYVWIPQZP" font="Comic Sans MS" border="none" textIndent="left"></tableRow>
<tableRow text="GXMDEEWAPZ" font="Comic Sans MS" border="none" textIndent="left"></tableRow>
<tableRow text="GXKKMVCZTO" font="Comic Sans MS" border="none" textIndent="left"></tableRow>
<tableRow text="ELECXSWHZH" font="Comic Sans MS" border="none" textIndent="left"></tableRow>
<tableRow text="RVOIHMUSXC" font="Comic Sans MS" border="none" textIndent="left"></tableRow>
<tableRow text="KBRHHWPEAY" font="Comic Sans MS" border="none" textIndent="left"></tableRow>
<tableRow text="MRRBUXRLLN" font="Comic Sans MS" border="none" textIndent="left"></tableRow>
<tableRow text="URABKOJMTV" font="Comic Sans MS" border="none" textIndent="left"></tableRow>
<tableRow text="KXLXMSZGGB" font="Comic Sans MS" border="none" textIndent="left"></tableRow>
<tableRow text="EQCYOQXGOD" font="Comic Sans MS" border="none" textIndent="left"></tableRow>
<tableRow text="ORNLRBJZFC" font="Comic Sans MS" border="none" textIndent="left"></tableRow>
<tableRow text="MDAURNHRBB" font="Comic Sans MS" border="none" textIndent="left"></tableRow>
</table>
<table>
<tableRow text="GKDRPTVNQK" font="Arial" border="none" textIndent="right"></tableRow>
<tableRow text="QLVCUINQMH" font="Arial" border="none" textIndent="right"></tableRow>
<tableRow text="UEULNPALOM" font="Arial" border="none" textIndent="right"></tableRow>
<tableRow text="FOFRBTALCT" font="Arial" border="none" textIndent="right"></tableRow>
<tableRow text="AQYFWWUVSP" font="Arial" border="none" textIndent="right"></tableRow>
<tableRow text="DXXUQIVXRH" font="Arial" border="none" textIndent="right"></tableRow>
</table>
<table>
<tableRow text="VQGDBLFJGN" font="Arial" border="full" textIndent="right"></tableRow>
<tableRow text="AYSMHUFLUA" font="Arial" border="full" textIndent="right"></tableRow>
<tableRow text="VJPYTFOMPO" font="Arial" border="full" textIndent="right"></tableRow>
<tableRow text="XPYCFPDZVF" font="Arial" border="full" textIndent="right"></tableRow>
<tableRow text="YVXNNTNAMF" font="Arial" border="full" textIndent="right"></tableRow>
<tableRow text="WDZQWJRRWQ" font="Arial" border="full" textIndent="right"></tableRow>
</table>
<table>
<tableRow text="LJUVOODDRN" font="Gotham" border="full" textIndent="left"></tableRow>
<tableRow text="PLPBMNPLPM" font="Gotham" border="full" textIndent="left"></tableRow>
<tableRow text="BACNUJMPPF" font="Gotham" border="full" textIndent="left"></tableRow>
<tableRow text="BYOUJCZFAC" font="Gotham" border="full" textIndent="left"></tableRow>
<tableRow text="ELEMOHPUDJ" font="Gotham" border="full" textIndent="left"></tableRow>
<tableRow text="PVQZKWVLFI" font="Gotham" border="full" textIndent="left"></tableRow>
<tableRow text="QFMEAXZSWT" font="Gotham" border="full" textIndent="left"></tableRow>
<tableRow text="VCEXQFIIJP" font="Gotham" border="full" textIndent="left"></tableRow>
<tableRow text="XRNQJDOPTS" font="Gotham" border="full" textIndent="left"></tableRow>
<tableRow text="EKQYRBCFFB" font="Gotham" border="full" textIndent="left"></tableRow>
<tableRow text="DGZTFCBHRZ" font="Gotham" border="full" textIndent="left"></tableRow>
<tableRow text="UMHVYIDASS" font="Gotham" border="full" textIndent="left"></tableRow>
</table>
<table>
<tableRow text="KSLBGGAXWX" font="Comic Sans MS" border="none" textIndent="center"></tableRow>
<tableRow text="VMOIWZQBXO" font="Comic Sans MS" border="none" textIndent="center"></tableRow>
<tableRow text="MNFHVASUPX" font="Comic Sans MS" border="none" textIndent="center"></tableRow>
<tableRow text="ZGKLLGSGXY" font="Comic Sans MS" border="none" textIndent="center"></tableRow>
</table>
<table>
<tableRow text="BCRJSGIKPX" font="Arial" border="row" textIndent="right"></tableRow>
<tableRow text="FKEHJTVLHH" font="Arial" border="row" textIndent="right"></tableRow>
<tableRow text="ZDRTSVHFMY" font="Arial" border="row" textIndent="right"></tableRow>
<tableRow text="PGLEMQMEPZ" font="Arial" border="row" textIndent="right"></tableRow>
<tableRow text="WTTWUGKESU" font="Arial" border="row" textIndent="right"></tableRow>
<tableRow text="VACSAAXZOK" font="Arial" border="row" textIndent="right"></tableRow>
<tableRow text="LHHNZDEZLU" font="Arial" border="row" textIndent="right"></tableRow>
<tableRow text="DUQENPKPUO" font="Arial" border="row" textIndent="right"></tableRow>
<tableRow text="PGACMVPPGT" font="Arial" border="row" textIndent="right"></tableRow>
<tableRow text="QSIMAQSXOO" font="Arial" border="row" textIndent="right"></tableRow>
<tableRow text="NUMZSKTSCA" font="Arial" border="row" textIndent="right"></tableRow>
<tableRow text="QOESYLXPVG" font="Arial" border="row" textIndent="right"></tableRow>
<tableRow text="QRSVUZQDDR" font="Arial" border="row" textIndent="right"></tableRow>
<tableRow text="VRONMZCXNW" font="Arial" border="row" textIndent="right"></tableRow>
<tableRow text="DIHUPAURVE" font="Arial" border="row" textIndent="right"></tableRow>
<tableRow text="EFMONZKAYL" font="Arial" border="row" textIndent="right"></tableRow>
<tableRow text="IKBHCWVCVJ" font="Arial" border="row" textIndent="right"></tableRow>
<tableRow text="YTPNZQBWQE" font="Arial" border="row" textIndent="right"></tableRow>
</table>
<table>
<tableRow text="XMKAAXGMHB" font="Arial" border="none" textIndent="left"></tableRow>
<tableRow text="YZMZQNLTVS" font="Arial" border="none" textIndent="left"></tableRow>
<tableRow text="OZPUCZHRJA" font="Arial" border="none" textIndent="left"></tableRow>
<tableRow text="BTCWAIYZQJ" font="Arial" border="none" textIndent="left"></tableRow>
<tableRow text="ORMWOBIEIO" font="Arial" border="none" textIndent="left"></tableRow>
<tableRow text="YEWXUWRJTO" font="Arial" border="none" textIndent="left"></tableRow>
<tableRow text="SVORSKVWCA" font="Arial" border="none" textIndent="left"></tableRow>
<tableRow text="FIDRPFVPFC" font="Arial" border="none" textIndent="left"></tableRow>
<tableRow text="JMTNUGFEHT" font="Arial" border="none" textIndent="left"></tableRow>
<tableRow text="MTGQMLMSPO" font="Arial" border="none" textIndent="left"></tableRow>
<tableRow text="YPLSOCHQXZ" font="Arial" border="none" textIndent="left"></tableRow>
<tableRow text="YHFJEHSXSR" font="Arial" border="none" textIndent="left"></tableRow>
<tableRow text="UHUMFHJFFI" font="Arial" border="none" textIndent="left"></tableRow>
</table>
<table>
<tableRow text="KUJTUIZIYI" font="Arial" border="full" textIndent="right"></tableRow>
<tableRow text="JVERQPNXHN" font="Arial" border="full" textIndent="right"></tableRow>
<tableRow text="FEEIYEFVWU" font="Arial" border="full" textIndent="right"></tableRow>
<tableRow text="DBXINFQUWA" font="Arial" border="full" textIndent="right"></tableRow>
<tableRow text="QVOVVRWKXI" font="Arial" border="full" textIndent="right"></tableRow>
<tableRow text="AEDYPOSSRV" font="Arial" border="full" textIndent="right"></tableRow>
<tableRow text="XOBBECDBAY" font="Arial" border="full" textIndent="right"></tableRow>
<tableRow text="VOABIBYXNQ" font="Arial" border="full" textIndent="right"></tableRow>
<tableRow text="YCIFCKFJVV" font="Arial" border="full" textIndent="right"></tableRow>
<tableRow text="OHBGLRSMIW" font="Arial" border="full" textIndent="right"></tableRow>
<tableRow text="VXPCGYRSFD" font="Arial" border="full" textIndent="right"></tableRow>
<tableRow text="BURHYKIVFN" font="Arial" border="full" textIndent="right"></tableRow>
<tableRow text="CMVKACYUBI" font="Arial" border="full" textIndent="right"></tableRow>
</table>
<table>
<tableRow text="VARMLVPNYC" font="Comic Sans MS" border="none" textIndent="center"></tableRow>
<tableRow text="VWENUZCGKC" font="Comic Sans MS" border="none" textIndent="center"></tableRow>
<tableRow text="XABZBJVUYV" font="Comic Sans MS" border="none" textIndent="center"></tableRow>
<tableRow text="QBNGMVHNDU" font="Comic Sans MS" border="none" textIndent="center"></tableRow>
<tableRow text="MNVLITQDLC" font="Comic Sans MS" border="none" textIndent="center"></tableRow>
<tableRow text="EVBOQVNMAQ" font="Comic Sans MS" border="none" textIndent="center"></tableRow>
<tableRow text="DJXAIBNYRG" font="Comic Sans MS" border="none" textIndent="center"></tableRow>
<tableRow text="MSPQJVZWLW" font="Comic Sans MS" border="none" textIndent="center"></tableRow>
</table>
<table>
<tableRow text="CLMYYAZDZZ" font="Arial" border="none" textIndent="center"></tableRow>
<tableRow text="BRZUKZGXBY" font="Arial" border="none" textIndent="center"></tableRow>
<tableRow text="HHWNSZCPKR" font="Arial" border="none" textIndent="center"></tableRow>
<tableRow text="CAHLTABTLK" font="Arial" border="none" textIndent="center"></tableRow>
<tableRow text="HTVDXNEYOA" font="Arial" border="none" textIndent="center"></tableRow>
<tableRow text="UHDUYWJOWH" font="Arial" border="none" textIndent="center"></tableRow>
<tableRow text="BJPMXAPQJN" font="Arial" border="none" textIndent="center"></tableRow>
</table>
<table>
<tableRow text="SWMXLQZLAN" font="Comic Sans MS" border="none" textIndent="center"></tableRow>
<tableRow text="PKJCMMACGG" font="Comic Sans MS" border="none" textIndent="center"></tableRow>
</table>
<table>
<tableRow text="JMOTNBBDMF" font="Arial" border="full" textIndent="center"></tableRow>
<tableRow text="VGADLYCAEY" font="Arial" border="full" textIndent="center"></tableRow>
<tableRow text="KGMADNZSYF" font="Arial" border="full" textIndent="center"></tableRow>
<tableRow text="PMAYPJJELV" font="Arial" border="full" textIndent="center"></tableRow>
<tableRow text="YJPWTMHFBA" font="Arial" border="full" textIndent="center"></tableRow>
<tableRow text="BNMJRIQCPI" font="Arial" border="full" textIndent="center"></tableRow>
<tableRow text="TTEUDOMRRH" font="Arial" border="full" textIndent="center"></tableRow>
<tableRow text="ILGLNENKJC" font="Arial" border="full" textIndent="center"></tableRow>
<tableRow text="NPIAPTPYSA" font="Arial" border="full" textIndent="center"></tableRow>
<tableRow text="SJGOHNRRDQ" font="Arial" border="full" textIndent="center"></tableRow>
<tableRow text="PDSACTTZWF" font="Arial" border="full" textIndent="center"></tableRow>
<tableRow text="CCIBPJQVYT" font="Arial" border="full" textIndent="center"></tableRow>
<tableRow text="UTCVAYPZPC" font="Arial" border="full" textIndent="center"></tableRow>
<tableRow text="CUHRRTLETZ" font="Arial" border="full" textIndent="center"></tableRow>
<tableRow text="RTDWXCZDPT" font="Arial" border="full" textIndent="center"></tableRow>
<tableRow text="ITGPUPPCYQ" font="Arial" border="full" textIndent="center"></tableRow>
<tableRow text="OHAGLYAAOD" font="Arial" border="full" textIndent="center"></tableRow>
<tableRow text="KBTRSKEDBJ" font="Arial" border="full" textIndent="center"></tableRow>
<tableRow text="ZJAJFJTWOH" font="Arial" border="full" textIndent="center"></tableRow>
</table>
<table>
<tableRow text="WELNESRDXC" font="Comic Sans MS" border="none" textIndent="right"></tableRow>
<tableRow text="TNCBHJRZID" font="Comic Sans MS" border="none" textIndent="right"></tableRow>
<tableRow text="APGBHVINIB" font="Comic Sans MS" border="none" textIndent="right"></tableRow>
<tableRow text="RJNFZELCCA" font="Comic Sans MS" border="none" textIndent="right"></tableRow>
<tableRow text="TNGXCAFEEU" font="Comic Sans MS" border="none" textIndent="right"></tableRow>
<tableRow text="JGIIUDSACU" font="Comic Sans MS" border="none" textIndent="right"></tableRow>
<tableRow text="SLWFFCAOJH" font="Comic Sans MS" border="none" textIndent="right"></tableRow>
</table>
</input>